Workbook

Sheet Admin
A2: Relocation fee???
H7: basic/PMI Bronze has 10% discount
A8: Service and Parts | B8: TS email, contract matters for discount
A9: Move | B9: contract doesn't matter
A10: Parts ONLY | B10: orders email, contract matters for discount
H11: protection on cells - turn into API
C15: Contract pricing - service
C16: Contract | D16: ='FSE Input'!B13 -> #REF! | E16: labor? | F16: cost | G16: premium contract | H16: 20% discount | I16: 10% dicsount | J16: final price
C17: part 1 | D17: =IF('FSE Input'!B17<>"",'FSE Input'!B17,IF('FSE Input'!B21<>"",'FSE Input'!B21,"")) -> On-Site Support (2 days) | E17: =IF(OR(ISNUMBER(SEARCH("site",D17)),ISNUMBER(SEARCH("service",D17)),ISNUMBER(SEARCH("support",D17))),"Yes","No") -> Yes | F17: =IF('FSE Input'!B19<>"",'FSE Input'!B19,IF('FSE Input'!B23<>"",'FSE Input'!B23,"")) -> 7571 | G17: =IF(E17="Yes", F17, IF(OR($D$16="Premium", $D$16="Gold", ISNUMBER(SEARCH("COMPLET",$D$16))), F17, "")) -> 7571 | H17: =IF(E17="Yes", F17, IF(OR($D$16="VALUE", $D$16="Silver", ISNUMBER(SEARCH("INTERMED",$D$16))), F17*0.8, "")) -> 7571 | I17: =IF(E17="Yes", F17, IF(OR($D$16="PMI", $D$16="Bronze", ISNUMBER(SEARCH("BASIC",$D$16))), F17*0.9, "")) -> 7571 | J17: =IF(E17="Yes", F17, IF(OR($D$16="Premium", $D$16="Gold", ISNUMBER(SEARCH("COMPLET",$D$16))), F17, IF(OR($D$16="VALUE", $D$16="Silver", ISNUMBER(SEARCH("INTERMED",$D$16))), F17*0.8, IF(OR($D$16="PMI", $D$16="Bronze", ISNUMBER(SEARCH("BASIC",$D$16))), F17*0.9, "" ) ) ) ) -> 7571
C18: part 2 | D18: =IF('FSE Input'!B25<>"",'FSE Input'!B25,IF('FSE Input'!B29<>"",'FSE Input'!B29,"")) | E18: =IF(OR(ISNUMBER(SEARCH("site",D18)),ISNUMBER(SEARCH("service",D18)),ISNUMBER(SEARCH("support",D18))),"Yes","No") -> No | F18: =IF('FSE Input'!B27<>"",'FSE Input'!B27,IF('FSE Input'!B31<>"",'FSE Input'!B31,"")) | G18: =IF(E18="Yes", F18, IF(OR($D$16="Premium", $D$16="Gold", ISNUMBER(SEARCH("COMPLET",$D$16))), F18, "")) -> #REF! | H18: =IF(E18="Yes", F18, IF(OR($D$16="VALUE", $D$16="Silver", ISNUMBER(SEARCH("INTERMED",$D$16))), F18*0.8, "")) -> #REF! | I18: =IF(E18="Yes", F18, IF(OR($D$16="PMI", $D$16="Bronze", ISNUMBER(SEARCH("BASIC",$D$16))), F18*0.9, "")) -> #REF! | J18: =IF(E18="Yes", F18, IF(OR($D$16="Premium", $D$16="Gold", ISNUMBER(SEARCH("COMPLET",$D$16))), F18, IF(OR($D$16="VALUE", $D$16="Silver", ISNUMBER(SEARCH("INTERMED",$D$16))), F18*0.8, IF(OR($D$16="PMI", $D$16="Bronze", ISNUMBER(SEARCH("BASIC",$D$16))), F18*0.9, "" ) ) ) ) -> #REF!
C19: part 3 | D19: =IF('FSE Input'!B33<>"",'FSE Input'!B33,IF('FSE Input'!B37<>"",'FSE Input'!B37,"")) | E19: =IF(OR(ISNUMBER(SEARCH("site",D19)),ISNUMBER(SEARCH("service",D19)),ISNUMBER(SEARCH("support",D19))),"Yes","No") -> No | F19: =IF('FSE Input'!B35<>"",'FSE Input'!B35,IF('FSE Input'!B39<>"",'FSE Input'!B39,"")) | G19: =IF(E19="Yes", F19, IF(OR($D$16="Premium", $D$16="Gold", ISNUMBER(SEARCH("COMPLET",$D$16))), F19, "")) -> #REF! | H19: =IF(E19="Yes", "", IF(OR($D$16="VALUE", $D$16="Silver", ISNUMBER(SEARCH("INTERMED",$D$16))), F19*0.8, "")) -> #REF! | I19: =IF(E19="Yes", F19, IF(OR($D$16="PMI", $D$16="Bronze", ISNUMBER(SEARCH("BASIC",$D$16))), F19*0.9, "")) -> #REF! | J19: =IF(E19="Yes", F19, IF(OR($D$16="Premium", $D$16="Gold", ISNUMBER(SEARCH("COMPLET",$D$16))), F19, IF(OR($D$16="VALUE", $D$16="Silver", ISNUMBER(SEARCH("INTERMED",$D$16))), F19*0.8, IF(OR($D$16="PMI", $D$16="Bronze", ISNUMBER(SEARCH("BASIC",$D$16))), F19*0.9, "" ) ) ) ) -> #REF!
C20: part 4 | D20: =IF('FSE Input'!B41<>"",'FSE Input'!B41,IF('FSE Input'!B45<>"",'FSE Input'!B45,"")) | E20: =IF(OR(ISNUMBER(SEARCH("site",D20)),ISNUMBER(SEARCH("service",D20)),ISNUMBER(SEARCH("support",D20))),"Yes","No") -> No | F20: =IF('FSE Input'!B43<>"",'FSE Input'!B43,IF('FSE Input'!B47<>"",'FSE Input'!B47,"")) | G20: =IF(E20="Yes", F20, IF(OR($D$16="Premium", $D$16="Gold", ISNUMBER(SEARCH("COMPLET",$D$16))), F20, "")) -> #REF! | H20: =IF(E20="Yes", F20, IF(OR($D$16="VALUE", $D$16="Silver", ISNUMBER(SEARCH("INTERMED",$D$16))), F20*0.8, "")) -> #REF! | I20: =IF(E20="Yes", F20, IF(OR($D$16="PMI", $D$16="Bronze", ISNUMBER(SEARCH("BASIC",$D$16))), F20*0.9, "")) -> #REF! | J20: =IF(E20="Yes", F20, IF(OR($D$16="Premium", $D$16="Gold", ISNUMBER(SEARCH("COMPLET",$D$16))), F20, IF(OR($D$16="VALUE", $D$16="Silver", ISNUMBER(SEARCH("INTERMED",$D$16))), F20*0.8, IF(OR($D$16="PMI", $D$16="Bronze", ISNUMBER(SEARCH("BASIC",$D$16))), F20*0.9, "" ) ) ) ) -> #REF!
C22: contract pricing - parts
C23: contract | D23: ='FSE Input'!E13 -> #REF! | E23: labor? | F23: cost | G23: premium | H23: 20% discount | I23: 10% discount | J23: final price
C24: part 1 | D24: =IF('FSE Input'!E17<>"",'FSE Input'!E17,IF('FSE Input'!E21<>"",'FSE Input'!E21,"")) -> On-Site Support (2 days) | E24: =IF(OR(ISNUMBER(SEARCH("site",D24)),ISNUMBER(SEARCH("service",D24)),ISNUMBER(SEARCH("support",D24))),"Yes","No") -> Yes | F24: =IF('FSE Input'!E19<>"",'FSE Input'!E19,IF('FSE Input'!E23<>"",'FSE Input'!E23,"")) -> 7571 | G24: =IF(E24="Yes", F24, IF(OR($D$23="Premium", $D$23="Gold", ISNUMBER(SEARCH("COMPLET",$D$23))), F24, "")) -> 7571 | H24: =IF(E24="Yes", F24, IF(OR($D$23="VALUE", $D$23="Silver", ISNUMBER(SEARCH("INTERMED",$D$23))), F24*0.8, "")) -> 7571 | I24: =IF(E24="Yes", F24, IF(OR($D$23="PMI", $D$23="Bronze", ISNUMBER(SEARCH("BASIC",$D$23))), F24*0.9, "")) -> 7571 | J24: =IF(E24="Yes", F24, IF(OR($D$23="Premium", $D$23="Gold", ISNUMBER(SEARCH("COMPLET",$D$23))), F24, IF(OR($D$23="VALUE", $D$23="Silver", ISNUMBER(SEARCH("INTERMED",$D$23))), F24*0.8, IF(OR($D$23="PMI", $D$23="Bronze", ISNUMBER(SEARCH("BASIC",$D$23))), F24*0.9, "" ) ) ) ) -> 7571
C25: part 2 | D25: =IF('FSE Input'!E25<>"",'FSE Input'!E25,IF('FSE Input'!E29<>"",'FSE Input'!E29,"")) -> Flow Cell Body | E25: =IF(OR(ISNUMBER(SEARCH("site",D25)),ISNUMBER(SEARCH("service",D25)),ISNUMBER(SEARCH("support",D25))),"Yes","No") -> No | F25: =IF('FSE Input'!E27<>"",'FSE Input'!E27,IF('FSE Input'!E31<>"",'FSE Input'!E31,"")) -> 268.71 | G25: =IF(E25="Yes", F25, IF(OR($D$23="Premium", $D$16="Gold", ISNUMBER(SEARCH("COMPLET",$D$23))), F25, "")) -> #REF! | H25: =IF(E25="Yes", F25, IF(OR($D$23="VALUE", $D$23="Silver", ISNUMBER(SEARCH("INTERMED",$D$23))), F25*0.8, "")) -> #REF! | I25: =IF(E25="Yes", F25, IF(OR($D$16="PMI", $D$16="Bronze", ISNUMBER(SEARCH("BASIC",$D$16))), F25*0.9, "")) -> #REF! | J25: =IF(E25="Yes", F25, IF(OR($D$23="Premium", $D$23="Gold", ISNUMBER(SEARCH("COMPLET",$D$23))), F25, IF(OR($D$23="VALUE", $D$23="Silver", ISNUMBER(SEARCH("INTERMED",$D$23))), F25*0.8, IF(OR($D$23="PMI", $D$23="Bronze", ISNUMBER(SEARCH("BASIC",$D$23))), F25*0.9, "" ) ) ) ) -> #REF!
C26: part 3 | D26: =IF('FSE Input'!E33<>"",'FSE Input'!E33,IF('FSE Input'!E37<>"",'FSE Input'!E37,"")) -> Mounting Plate | E26: =IF(OR(ISNUMBER(SEARCH("site",D26)),ISNUMBER(SEARCH("service",D26)),ISNUMBER(SEARCH("support",D26))),"Yes","No") -> No | F26: =IF('FSE Input'!E35<>"",'FSE Input'!E35,IF('FSE Input'!E39<>"",'FSE Input'!E39,"")) -> 7.76 | G26: =IF(E26="Yes", F26, IF(OR($D$23="Premium", $D$23="Gold", ISNUMBER(SEARCH("COMPLET",$D$23))), F26, "")) -> #REF! | H26: =IF(E26="Yes", "", IF(OR($D$23="VALUE", $D$23="Silver", ISNUMBER(SEARCH("INTERMED",$D$23))), F26*0.8, "")) -> #REF! | I26: =IF(E26="Yes", F26, IF(OR($D$16="PMI", $D$16="Bronze", ISNUMBER(SEARCH("BASIC",$D$16))), F26*0.9, "")) -> #REF! | J26: =IF(E26="Yes", F26, IF(OR($D$23="Premium", $D$23="Gold", ISNUMBER(SEARCH("COMPLET",$D$23))), F26, IF(OR($D$23="VALUE", $D23="Silver", ISNUMBER(SEARCH("INTERMED",$D$23))), F26*0.8, IF(OR($D$23="PMI", $D$23="Bronze", ISNUMBER(SEARCH("BASIC",$D$23))), F26*0.9, "" ) ) ) ) -> #REF!
C27: part 4 | D27: =IF('FSE Input'!E41<>"",'FSE Input'!E41,IF('FSE Input'!E45<>"",'FSE Input'!E45,"")) -> generator | E27: =IF(OR(ISNUMBER(SEARCH("site",D27)),ISNUMBER(SEARCH("service",D27)),ISNUMBER(SEARCH("support",D27))),"Yes","No") -> No | F27: =IF('FSE Input'!E43<>"",'FSE Input'!E43,IF('FSE Input'!E47<>"",'FSE Input'!E47,"")) -> 800 | G27: =IF(E27="Yes", F27, IF(OR($D$23="Premium", $D$23="Gold", ISNUMBER(SEARCH("COMPLET",$D$23))), F27, "")) -> #REF! | H27: =IF(E27="Yes", F27, IF(OR($D$23="VALUE", $D$23="Silver", ISNUMBER(SEARCH("INTERMED",$D$23))), F27*0.8, "")) -> #REF! | I27: =IF(E27="Yes", F27, IF(OR($D$16="PMI", $D$16="Bronze", ISNUMBER(SEARCH("BASIC",$D$16))), F27*0.9, "")) -> #REF! | J27: =IF(E27="Yes", F27, IF(OR($D$23="Premium", $D$23="Gold", ISNUMBER(SEARCH("COMPLET",$D$23))), F27, IF(OR($D$23="VALUE", $D$23="Silver", ISNUMBER(SEARCH("INTERMED",$D$23))), F27*0.8, IF(OR($D$23="PMI", $D$23="Bronze", ISNUMBER(SEARCH("BASIC",$D$23))), F27*0.9, "" ) ) ) ) -> #REF!
D34: need to include the if not listed here | F34: test if all work for if not listed
D35: note
D36: add a little popup that says if the contract is value, amke sure this is not the customer's first repair if so no quote needed
D37: how to do pricing? which cell has numbers? or combine everything into one

Sheet FSE Input
A1: What are you quoting?
A2: Service and Parts
A6: Use "Cytek Service Quoting" Tab to print quote | D6: Use "Cytek Parts Quoting" Tab to print quote
A7: CUSTOMER INFORMATION - SERVICE QUOTE | D7: Customer information - Parts Quote
A8: Name of customer requesting service/part: | B8: Alyssa Sanfillipo | D8: Name of customer requesting service/part: | E8: Mike Waring
A9: Instrument SN: | B9: R0732 | D9: Instrument SN: | E9: U1399
A10: Facility name: | B10: =VLOOKUP(B9,#REF!,2,FALSE) -> #REF! | D10: Facility name: | E10: =VLOOKUP(E9,#REF!,2,FALSE) -> #REF!
A11: Shortened Facility name | B11: =VLOOKUP(B10,#REF!,2,FALSE) -> #REF! | D11: Shortened Facility name | E11: =VLOOKUP(E10,#REF!,2,FALSE) -> #REF!
A12: Facility Address: | B12: =VLOOKUP(B9,#REF!,19,FALSE) -> #REF! | D12: Facility Address: | E12: =VLOOKUP(E9,#REF!,19,FALSE) -> #REF!
A13: Contract type: | B13: =VLOOKUP(B9,#REF!,9,FALSE) -> #REF! | D13: Contract type: | E13: =VLOOKUP(E9,#REF!,9,FALSE) -> #REF!
A15: SERVICE TYPE/PART NAME - SERVICE QUOTE | D15: SERVICE TYPE/PART NAME - PARTS QUOTE
A16: PART 1 | D16: PART 1
A17: Service Type/ Part Name | B17: On-Site Support (2 days) | D17: Service Type/ Part Name | E17: On-Site Support (2 days)
A18: Service Type/Part Number | B18: =IF(B17="","",VLOOKUP(B17,'Pricing Data'!A$2:H5436,7,FALSE)) -> 60020 | D18: Service Type/Part Number | E18: =IF(E17="","",VLOOKUP(E17,'Pricing Data'!A$2:H5436,7,FALSE)) -> 60020
A19: Service Type/ Part Price | B19: =IF(B17="","",VLOOKUP(B17,'Pricing Data'!A$2:H5436,4,FALSE)) -> 7571 | D19: Service Type/ Part Price | E19: =IF(E17="","",VLOOKUP(E17,'Pricing Data'!A$2:H5436,4,FALSE)) -> 7571
A20: Quantity | B20: 1 | D20: Quantity | E20: 1
A21: Service Type / Part Name (if not listed) | D21: Service Type / Part Name (if not listed)
A22: Service Type Part Number (if not listed) | D22: Service Type Part Number (if not listed)
A23: Price of Service Type / Part (if not listed) | D23: Price of Service Type / Part (if not listed)
A24: PART 2 | D24: PART 2
A25: Service Type/ Part Name | D25: Service Type/ Part Name | E25: Flow Cell Body
A26: Service Type/Part Number | B26: =IF(B25="","",VLOOKUP(B25,'Pricing Data'!A$2:H5436,7,FALSE)) | D26: Service Type/Part Number | E26: =IF(E25="","",VLOOKUP(E25,'Pricing Data'!A$2:H5444,7,FALSE)) -> N0-00011
A27: Service Type/ Part Price | B27: =IF(B25="","",VLOOKUP(B25,'Pricing Data'!A$2:H5436,4,FALSE)) | D27: Service Type/ Part Price | E27: =IF(E25="","",VLOOKUP(E25,'Pricing Data'!A$2:H5444,4,FALSE)) -> 268.71
A28: Quantity | D28: Quantity | E28: 1
A29: Service Type / Part Name (if not listed) | D29: Service Type / Part Name (if not listed)
A30: Service Type Part Number (if not listed) | D30: Service Type Part Number (if not listed)
A31: Price of Service Type / Part (if not listed) | D31: Price of Service Type / Part (if not listed)
A32: PART 3 | D32: PART 3
A33: Service Type/ Part Name | D33: Service Type/ Part Name | E33: Mounting Plate
A34: Service Type/Part Number | B34: =IF(B33="","",VLOOKUP(B33,'Pricing Data'!A$2:H5436,7,FALSE)) | D34: Service Type/Part Number | E34: =IF(E33="","",VLOOKUP(E33,'Pricing Data'!A$2:H5452,7,FALSE)) -> N0-00002
A35: Service Type/ Part Price | B35: =IF(B33="","",VLOOKUP(B33,'Pricing Data'!A$2:H5436,4,FALSE)) | D35: Service Type/ Part Price | E35: =IF(E33="","",VLOOKUP(E33,'Pricing Data'!A$2:H5452,4,FALSE)) -> 7.76
A36: Quantity | D36: Quantity | E36: 1
A37: Service Type / Part Name (if not listed) | D37: Service Type / Part Name (if not listed)
A38: Service Type Part Number (if not listed) | D38: Service Type Part Number (if not listed)
A39: Price of Service Type / Part (if not listed) | D39: Price of Service Type / Part (if not listed)
A40: PART 4 | D40: PART 4
A41: Service Type/ Part Name | D41: Service Type/ Part Name
A42: Service Type/Part Number | B42: =IF(B41="","",VLOOKUP(B41,'Pricing Data'!A$2:H5436,7,FALSE)) | D42: Service Type/Part Number | E42: =IF(E41="","",VLOOKUP(E41,'Pricing Data'!A$2:H5460,7,FALSE))
A43: Service Type/ Part Price | B43: =IF(B41="","",VLOOKUP(B41,'Pricing Data'!A$2:H5436,4,FALSE)) | D43: Service Type/ Part Price | E43: =IF(E41="","",VLOOKUP(E41,'Pricing Data'!A$2:H5460,4,FALSE))
A44: Quantity | D44: Quantity | E44: 1
A45: Service Type / Part Name (if not listed) | D45: Service Type / Part Name (if not listed) | E45: generator
A46: Service Type Part Number (if not listed) | D46: Service Type Part Number (if not listed) | E46: u1093
A47: Price of Service Type / Part (if not listed) | D47: Price of Service Type / Part (if not listed) | E47: 800

Sheet Cytek Service Quoting
C2: ='FSE Input'!B8 -> Alyssa Sanfillipo | F2: ="QUOTE#: "&'FSE Input'!$B$11&" "&'FSE Input'!$B$9 -> #REF!
C3: ='FSE Input'!B10 -> #REF!
C4: ='FSE Input'!B12 -> #REF!
C7: Item | D7: Description | E7: Product Number | F7: Qty | G7: List Price | H7: Net Price | I7: Ext. Price
C8: =IF(D8="", "", "1") -> 1 | D8: =IF('FSE Input'!B17<>"", 'FSE Input'!B17, IF('FSE Input'!B21<>"", 'FSE Input'!B21, "")) -> On-Site Support (2 days) | E8: =IF('FSE Input'!B18<>"", 'FSE Input'!B18, IF('FSE Input'!B22<>"", 'FSE Input'!B22, "")) -> 60020 | F8: =IF(ISBLANK('FSE Input'!B20),"",'FSE Input'!B20) -> 1 | G8: =IF('FSE Input'!B19<>"", 'FSE Input'!B19, IF('FSE Input'!B23<>"", 'FSE Input'!B23, "")) -> 7571 | H8: =IF(Admin!D17<>"",Admin!J17,"") -> 7571 | I8: =IF(G8="","",H8*F8) -> 7571
C9: =IF(D9="", "", "2") | D9: =IF('FSE Input'!B25<>"", 'FSE Input'!B25, IF('FSE Input'!B29<>"", 'FSE Input'!B29, "")) | E9: =IF('FSE Input'!B26<>"", 'FSE Input'!B26, IF('FSE Input'!B30<>"", 'FSE Input'!B30, "")) | F9: =IF(ISBLANK('FSE Input'!B28),"",'FSE Input'!B28) | G9: =IF('FSE Input'!B27<>"", 'FSE Input'!B27, IF('FSE Input'!B31<>"", 'FSE Input'!B31, "")) | H9: =IF(Admin!D18<>"",Admin!J18,"") | I9: =IF(G9="","",H9*F9)
C10: =IF(D10="", "", "3") | D10: =IF('FSE Input'!B33<>"", 'FSE Input'!B33, IF('FSE Input'!B37<>"", 'FSE Input'!B37, "")) | E10: =IF('FSE Input'!B34<>"", 'FSE Input'!B34, IF('FSE Input'!B38<>"", 'FSE Input'!B38, "")) | F10: =IF(ISBLANK('FSE Input'!B36),"",'FSE Input'!B36) | G10: =IF('FSE Input'!B35<>"", 'FSE Input'!B35, IF('FSE Input'!B39<>"", 'FSE Input'!B39, "")) | H10: =IF(Admin!D19<>"",Admin!J19,"") | I10: =IF(G10="","",H10*F10)
C11: =IF(D11="", "", "4") | D11: =IF('FSE Input'!B41<>"", 'FSE Input'!B41, IF('FSE Input'!B45<>"", 'FSE Input'!B45, "")) | E11: =IF('FSE Input'!B42<>"", 'FSE Input'!B42, IF('FSE Input'!B46<>"", 'FSE Input'!B46, "")) | F11: =IF(ISBLANK('FSE Input'!B44),"",'FSE Input'!B44) | G11: =IF('FSE Input'!B43<>"", 'FSE Input'!B43, IF('FSE Input'!B47<>"", 'FSE Input'!B47, "")) | H11: =IF(Admin!D20<>"",Admin!J20,"") | I11: =IF(G11="","",H11*F11)
C13: Shipping & Handling Estimate
C14: Total | I14: =SUM(I15,I8:I11) -> 7571
D16: Pre-Inspection/Recertification
G101: ="QUOTE#: "&'FSE Input Old'!$D$3&" "&'FSE Input Old'!$B$3 -> #REF!
G153: ="QUOTE#: "&'FSE Input Old'!$D$3&" "&'FSE Input Old'!$B$3 -> #REF!

Sheet Cytek Parts Quoting
C2: ='FSE Input'!E8 -> Mike Waring | F2: ="QUOTE#: "&'FSE Input'!$E$11&" "&'FSE Input'!$E$9 -> #REF!
C3: ='FSE Input'!E10 -> #REF!
C4: ='FSE Input'!E12 -> #REF!
C7: Item | D7: Description | E7: Product Number | F7: Qty | G7: List Price | H7: Net Price | I7: Ext. Price
C8: =IF(D8="", "", "1") -> 1 | D8: =IF('FSE Input'!E17<>"", 'FSE Input'!E17, IF('FSE Input'!E21<>"", 'FSE Input'!E21, "")) -> On-Site Support (2 days) | E8: =IF('FSE Input'!E18<>"", 'FSE Input'!E18, IF('FSE Input'!E22<>"", 'FSE Input'!E22, "")) -> 60020 | F8: =IF(ISBLANK('FSE Input'!E20),"",'FSE Input'!E20) -> 1 | G8: =IF('FSE Input'!E19<>"", 'FSE Input'!E19, IF('FSE Input'!E23<>"", 'FSE Input'!E23, "")) -> 7571 | H8: =IF(Admin!D24<>"",Admin!J24,"") -> 7571 | I8: =IF(G8="","",H8*F8) -> 7571
C9: =IF(D9="", "", "2") -> 2 | D9: =IF('FSE Input'!E25<>"", 'FSE Input'!E25, IF('FSE Input'!E29<>"", 'FSE Input'!E29, "")) -> Flow Cell Body | E9: =IF('FSE Input'!E26<>"", 'FSE Input'!E26, IF('FSE Input'!E30<>"", 'FSE Input'!E30, "")) -> N0-00011 | F9: =IF(ISBLANK('FSE Input'!E28),"",'FSE Input'!E28) -> 1 | G9: =IF('FSE Input'!E27<>"", 'FSE Input'!E27, IF('FSE Input'!E31<>"", 'FSE Input'!E31, "")) -> 268.71 | H9: =IF(Admin!D25<>"",Admin!J25,"") -> #REF! | I9: =IF(G9="","",H9*F9) -> #REF!
C10: =IF(D10="", "", "3") -> 3 | D10: =IF('FSE Input'!E33<>"", 'FSE Input'!E33, IF('FSE Input'!E37<>"", 'FSE Input'!E37, "")) -> Mounting Plate | E10: =IF('FSE Input'!E34<>"", 'FSE Input'!E34, IF('FSE Input'!E38<>"", 'FSE Input'!E38, "")) -> N0-00002 | F10: =IF(ISBLANK('FSE Input'!E36),"",'FSE Input'!E36) -> 1 | G10: =IF('FSE Input'!E35<>"", 'FSE Input'!E35, IF('FSE Input'!E39<>"", 'FSE Input'!E39, "")) -> 7.76 | H10: =IF(Admin!D26<>"",Admin!J26,"") -> #REF! | I10: =IF(G10="","",H10*F10) -> #REF!
C11: =IF(D11="", "", "4") -> 4 | D11: =IF('FSE Input'!E41<>"", 'FSE Input'!E41, IF('FSE Input'!E45<>"", 'FSE Input'!E45, "")) -> generator | E11: =IF('FSE Input'!E42<>"", 'FSE Input'!E42, IF('FSE Input'!E46<>"", 'FSE Input'!E46, "")) -> u1093 | F11: =IF(ISBLANK('FSE Input'!E44),"",'FSE Input'!E44) -> 1 | G11: =IF('FSE Input'!E43<>"", 'FSE Input'!E43, IF('FSE Input'!E47<>"", 'FSE Input'!E47, "")) -> 800 | H11: =IF(Admin!D27<>"",Admin!J27,"") -> #REF! | I11: =IF(G11="","",H11*F11) -> #REF!
C13: Shipping & Handling Estimate
C14: Total | I14: =SUM(I15,I8:I11) -> #REF!
G49: ="QUOTE#: "&'FSE Input Old'!$D$3&" "&'FSE Input Old'!$B$3 -> #REF!
G101: ="QUOTE#: "&'FSE Input Old'!$D$3&" "&'FSE Input Old'!$B$3 -> #REF!
G153: ="QUOTE#: "&'FSE Input Old'!$D$3&" "&'FSE Input Old'!$B$3 -> #REF!

Sheet Asset Data
A1: Product: Product Name | B1: Serial Number | C1: Install Date | D1: Synced Contract: Contract Number | E1: Status | F1: Account Name | G1: Synced Contract: Contract End Date | H1: Country | I1: Synced Contract: Contract Type
A2: Guava easyCyte 6-2L, Boxed Instrument | B2: 10000006001 | C2: 43369 | E2: Installed | F2: Institut Universitaire de Technologie (IUT) Louis Pasteur
A3: Guava PCA Base System, with software, Obsolete | B3: 1000880 | C3: 40407 | E3: Installed | F3: Shanxi Medical University????????
A4: Amnis ImageStreamX MkII System w/ INSPIRE & IDEAS Software | B4: 100220 | C4: 43217 | E4: Deinstalled | F4: FUWAI HOSPITAL
A5: xP4 Upgrade | B5: 1040 | C5: 38955 | E5: Installed | F5: Thermo Fisher Scientific - Life Technologies Corporation
A6: MUSE CELL ANALYZER SYSTEM | B6: 11 | C6: 41619 | E6: Installed | F6: QUALITY ASSISTANCE
A7: Guava PCA Base System, with software, Obsolete | B7: 1100900 | C7: 40842 | E7: Installed | F7: FIBROCELL SCIENCE INC
A8: MUSE CELL ANALYZER SYSTEM | B8: 11111-018838 | C8: 41855 | E8: Installed | F8: LPU GMBH
A9: xP4 Upgrade | B9: 1151 | C9: 40084 | E9: Installed | F9: University of Utah
A10: Automatic Micro-Sampler CE | B10: 1314 | C10: 40864 | E10: Installed | F10: TU Delft_microbiology
A11: xP4 Upgrade | B11: 1316 | C11: 40835 | E11: Installed | F11: Seattle Pacific University
A12: xP5 Upgrade | B12: 1343 | C12: 40928 | E12: Installed | F12: Aptevo Research and Development LLC
A13: xP5 Upgrade | B13: 1345 | C13: 40948 | E13: Installed | F13: Affymetrix
... A38: FlowKart | B38: 1516 | C38: 43277 | E38: Installed | F38: Regeneron Pharmaceuticals Inc
B39: 2800060146R | C39: 39052 | E39: Deinstalled | F39: ExcellGene SA
B40: 3630090414 | C40: 40014 | E40: Deinstalled | F40: REIN TX (PREV. AILERON THERAPEUTICS)
A41: Guava easyCyte 6-2L, Boxed Instrument | B41: 6620106007 | C41: 40492 | E41: Deinstalled | F41: NYU Langone Health
A42: Guava easyCyte 6-2L, Boxed Instrument | B42: 6620126046 | C42: 40970 | E42: Deinstalled | F42: Eberhard Karls Universität Tübingen
A43: Guava easyCyte 6-2L, Boxed Instrument | B43: 6620126092 | C43: 41373 | E43: Deinstalled | F43: Merck KGaA - Merck Biodevelopment SAS
A44: Guava easyCyte 8SL, Boxed Instrument | B44: 6620128023 | C44: 41297 | E44: Deinstalled | F44: AstraZeneca Pharmaceuticals LP - R&D Boston MA
B45: 662012S008 | C45: 40955 | E45: Installed | F45: FRAUNHOFER-INSTITUT FUR ZELLTHERAPIE UND IMMUNOLOGIE IZI
B46: 662012S015 | C46: 41353 | E46: Installed | F46: UK Health Security Agency
A47: Guava easyCyte 6-2L, Boxed Instrument | B47: 6620136106 | C47: 41439 | E47: Deinstalled | F47: Karlsruher Institut für Technologie
B48: 662013S017 | C48: 41338 | E48: Installed | F48: MRC Laboratory of Medical Sciences (LMS)
B49: 662013S020 | C49: 41540 | E49: Installed | F49: Hôpitaux Universitaires - Pitié Salpêtrière
A50: Guava easyCyte 5SL, Boxed Instrument | B50: 6620145182 | C50: 41921 | E50: Deinstalled | F50: Cook MyoSite Inc
B51: 662014S024 | C51: 41988 | E51: Installed | F51: Howard Hughes Medical Institute (HHMI)
B52: 6620-R6144 | C52: 42139 | E52: Deinstalled | F52: INTERTEK PHARMACEUTICALS
A53: Guava easyCyte 6HT-2L, Boxed Instrument | B53: 6735116035 | C53: 40721 | E53: Deinstalled | F53: Thermo Fisher Scientific - Guilford CT
A54: Guava easyCyte 8HT, Boxed Instrument | B54: 6735118079 | C54: 40925 | E54: Deinstalled | F54: Massachusetts Institute of Technology (MIT)
B55: 6735125108 | C55: 41395 | E55: Deinstalled | F55: University of Pittsburgh
B56: 6735125120 | C56: 41200 | E56: Deinstalled | F56: Millipore Sigma (formerly Mirius Bio LLC)
A57: Guava easyCyte 6HT-2L, Boxed Instrument | B57: 6735125124A | C57: 41793 | E57: Deinstalled | F57: BEIJING WANTAI BIOLOGICAL PHARMACY ENTERPRISE CO LTD
B58: 6735125136 | C58: 41281 | E58: Deinstalled | F58: IPSEN (PREVIOUSLY EPIZYME INC)
A59: Guava easyCyte 6HT-2L, Boxed Instrument | B59: 6735126101 | C59: 41199 | E59: Deinstalled | F59: MEDIAGNOST GMBH
A60: Guava easyCyte 8HT, Boxed Instrument | B60: 6735128085 | C60: 40935 | E60: Deinstalled | F60: University of Houston
A61: Guava easyCyte 8HT, Boxed Instrument | B61: 6735128146 | C61: 41206 | E61: Deinstalled | F61: University of Virginia
A62: Guava easyCyte 8HT, Boxed Instrument | B62: 6735128160 | C62: 41473 | E62: Deinstalled | F62: XIANGYA HOSPITAL CENTRAL SOUTH UNIVERSITY
A63: Guava easyCyte 8HT, Boxed Instrument | B63: 6735128167 | C63: 41309 | E63: Deinstalled | F63: University of Texas at Austin
B64: 673512S013 | C64: 41000 | E64: Installed | F64: University of California, Berkeley
B65: 673512S016 | C65: 41135 | E65: Installed | F65: University of Texas Southwestern
B66: 673512S017 | C66: 41109 | E66: Installed | F66: Forschungsinstitut für Molekulare Pathologie GmbH (IMP)
A67: Guava easyCyte 5HT HPL | B67: 673512S018 | C67: 41191 | E67: Deinstalled | F67: GlaxoSmithKline (GSK) Belgium - Wavre
B68: 6735135151 | C68: 41480 | E68: Deinstalled | F68: Icahn School of Medicine at Mount Sinai (ISMMS)
B69: 6735135159 | C69: 41386 | E69: Deinstalled | F69: ExcellGene SA
A70: Guava easyCyte 6HT-2L, Boxed Instrument | B70: 6735136133 | C70: 41501 | E70: Deinstalled | F70: Northwestern University
A71: Guava easyCyte 8HT, Boxed Instrument | B71: 6735138187 | C71: 42437 | E71: Deinstalled | F71: PASPA PHARMACEUTICALS
A72: Guava easyCyte 8HT, Boxed Instrument | B72: 6735138195 | C72: 41473 | E72: Deinstalled | F72: Boehringer Ingelheim Pharma GmbH & Co. KG
A73: Guava easyCyte 8HT, Boxed Instrument | B73: 6735138226 | C73: 41611 | E73: Deinstalled | F73: Columbia University Irving Medical Center
A74: Guava easyCyte 8HT, Boxed Instrument | B74: 6735138231 | C74: 41659 | E74: Deinstalled | F74: University of Pennsylvania
A75: Guava easyCyte 8HT, Boxed Instrument | B75: 6735138233 | C75: 41753 | E75: Deinstalled | F75: Boehringer Ingelheim Pharma GmbH & Co. KG
A76: Guava easyCyte 5SL, Boxed Instrument | B76: 673513S020 | C76: 41496 | E76: Installed | F76: McGill University
B77: 673513S024 | C77: 41501 | E77: Installed | F77: Deutsche Krebsforschungszentrum (DKFZ)
B78: 673513S025 | C78: 41457 | E78: Installed | F78: PIVOT BIO
B79: 6735145216 | C79: 41781 | E79: Deinstalled | F79: Icahn School of Medicine at Mount Sinai (ISMMS)
B80: 6735145217 | C80: 41801 | E80: Deinstalled | F80: AbbVie Inc - Bay Area
B81: 6735145222 | C81: 41809 | E81: Deinstalled | F81: ExcellGene SA
B82: 6735145231 | C82: 42128 | E82: Deinstalled | F82: Beth Israel Deaconess Medical Center Inc
B83: 6735145232 | C83: 41918 | E83: Deinstalled | F83: Sanofi R&D Vaccins - Marcy l'etoile
B84: 6735145241 | C84: 42382 | E84: Deinstalled | F84: NEXTCELL PHARMA AB
B85: 6735145247 | C85: 41955 | E85: Deinstalled | F85: MilliporeSigma
A86: Guava easyCyte 6HT-2L, Boxed Instrument | B86: 6735146183 | C86: 41908 | E86: Deinstalled | F86: Shanghai Tech University (???????
A87: Guava easyCyte 6HT-2L, Boxed Instrument | B87: 6735146190 | C87: 41862 | E87: Deinstalled | F87: BEIJING WANTAI BIOLOGICAL PHARMACY ENTERPRISE CO LTD
A88: Guava easyCyte 6HT-2L, Boxed Instrument | B88: 6735146218 | C88: 41858 | E88: Deinstalled | F88: Antibody Solutions
A89: Guava easyCyte 6HT-2L, Boxed Instrument | B89: 6735146219 | C89: 41865 | E89: Deinstalled | F89: Memorial Sloan Kettering Cancer Center
A90: Guava easyCyte 6HT-2L, Boxed Instrument | B90: 6735146241 | C90: 42138 | E90: Deinstalled | F90: Xinxiang Medical University (??????
A91: Guava easyCyte 6HT-2L, Boxed Instrument | B91: 6735146244 | C91: 42032 | E91: Deinstalled | F91: NORDIC NANOVECTOR ASA
A92: Guava easyCyte 8HT, Boxed Instrument | B92: 6735148248 | C92: 41835 | E92: Customer Owned Equipment Not in Use | F92: Boehringer Ingelheim Pharma GmbH & Co. KG
A93: Guava easyCyte 8HT, Boxed Instrument | B93: 6735148253 | C93: 41807 | E93: Deinstalled | F93: Revvity UK (Oxford Immunotec Limited)
A94: Guava easyCyte 8HT, Boxed Instrument | B94: 6735148261 | C94: 42317 | E94: Deinstalled | F94: Revvity UK (Oxford Immunotec Limited)
B95: 673514S030 | C95: 41961 | E95: Installed | F95: Dharmacon Inc
B96: 673514S031 | C96: 41983 | E96: Installed | F96: Thermo Fisher Scientific (Schweiz) AG
B97: 673514S034 | C97: 42137 | E97: Installed | F97: University of Cambridge
B98: 673514S194 | C98: 41829 | E98: Installed | F98: Inter Scientific Limited
B99: 673514S205 | C99: 41738 | E99: Installed | F99: Georgia Institute Of Technology
B100: 673514S211 | C100: 41851 | E100: Installed | F100: MAX VON PETTENKOFER INSTITUT
B101: 673514S216 | C101: 42030 | E101: Installed | F101: Christian-Albrechts-Universität zu Kiel (CAU Kiel)
B102: 673515S037 | C102: 42151 | E102: Installed | F102: École Polytechnique Fédérale de Lausanne (EPFL)
B103: 673515S040 | C103: 42247 | E103: Installed | F103: Columbia University Irving Medical Center
B104: 67351S027 | C104: 41671 | E104: Installed | F104: University of Cambridge
B105: 6735-R5107 | C105: 41102 | E105: Deinstalled | F105: EMD Serono Inc
B106: 6735-R5194 | C106: 41741 | E106: Deinstalled | F106: University of Edinburgh
A107: Instrument, Top Level, Easycyte, 5HT | B107: 6735-R5201-1 | C107: 44120 | E107: Deinstalled | F107: Johns Hopkins Health System Corporation
B108: 6735-R6072 | C108: 40960 | E108: Installed | F108: MEDIGENE AG
A109: Guava easyCyte 6HT-2L, Boxed Instrument | B109: 6735-R6133 | C109: 42158 | E109: Installed | F109: Proteos Inc
A110: Guava easyCyte 6HT-2L, Boxed Instrument | B110: 6735-R6218 | C110: 42303 | E110: Deinstalled | F110: LUMINEX OWNED EQUIPMENT
B111: 6735-R8026 | C111: 41102 | E111: Deinstalled | F111: Eurofins - St Charles MO
B112: 6735-R8041 | C112: 41151 | E112: Deinstalled | F112: SERVICEMAX GENERIC ACCOUNT
B113: 6735-R8190 | C113: 41486 | E113: Deinstalled | F113: University of Ottawa
B114: 6735-R8193B | C114: 42066 | E114: Deinstalled | F114: Universitätsklinikum Magdeburg
B115: 6735-R8253 | C115: 42478 | E115: Deinstalled | F115: University of Colorado Anschutz Medical Campus
A116: MUSE CELL ANALYZER SYSTEM | B116: 7200120477 | C116: 41247 | E116: Deinstalled | F116: Cancer Research UK Manchester Institute (CRUK MI)
A117: MUSE CELL ANALYZER SYSTEM | B117: 7200120700 | C117: 42325 | E117: Deinstalled | F117: ST BREAHMANAS COLLEGE
A118: MUSE CELL ANALYZER SYSTEM | B118: 7200121446 | C118: 42200 | E118: Deinstalled | F118: Etablissement Francais du Sang (EFS) - Occitanie
A119: Muse Open Module Software | B119: 7200121496-1 | C119: 42220 | E119: Installed | F119: INSTITUT DE RECHERCHE BIOMEDICALE DES ARMEES (IRBA)
B120: 7200121532 | C120: 42317 | E120: Deinstalled | F120: NIHON UNIVERSITY ITABASHI HOSPITAL
A121: MUSE CELL ANALYZER SYSTEM | B121: 720015001 | C121: 42819 | E121: Deinstalled | F121: BIOTEC SYSTEMS
A122: Muse Open Module Software | B122: 7200150430-1 | C122: 42767 | E122: Installed | F122: KOMA BIOTECH INC
A123: MUSE CELL ANALYZER SYSTEM | B123: 7200150688 | C123: 43124 | E123: Installed | F123: Cytek Biosciences, Inc HQ
A124: MUSE CELL ANALYZER SYSTEM | B124: 7200150709 | C124: 42982 | E124: Deinstalled | F124: MABTECH AB
...

Sheet Pricing Data
A1: Display Name | B1: Last Purchase Price | C1: Sale Unit | D1: Unit Price | E1: Price Level | F1: Currency | G1: Part Number | H1: Item Internal ID
A2: Value contract deductible | D2: 750 | F2: US Dollar | G2: Value
A3: On-Site Support (2 days) | D3: 7571 | F3: US Dollar | G3: 60020
A4: Basic contract deductible | F4: US Dollar
A5: Vacuum Manifold | B5: 58.56 | C5: Each | D5: 274.64 | E5: List Price | F5: US Dollar | G5: N0-00001 | H5: 34749
A6: Mounting Plate | B6: 2.12 | C6: Each | D6: 7.76 | E6: List Price | F6: US Dollar | G6: N0-00002 | H6: 16742
A7: Valve Guide | B7: 7.46 | C7: Each | D7: 22.38 | E7: List Price | F7: US Dollar | G7: N0-00003 | H7: 16743
A8: Pinch Hammer | B8: 0 | C8: Each | D8: 33.57 | E8: List Price | F8: US Dollar | G8: N0-00004 | H8: 16744
A9: Pinch Head | B9: 0 | C9: Each | D9: 80.61 | E9: List Price | F9: US Dollar | G9: N0-00005 | H9: 16745
A10: DeGasser Bracket | B10: 3.34 | C10: Each | D10: 12.53 | E10: List Price | F10: US Dollar | G10: N0-00006 | H10: 16746
A11: Lens Retaining Cover | B11: 3.6 | C11: Each | D11: 37.38 | E11: List Price | F11: US Dollar | G11: N0-00009 | H11: 16747
A12: Lens Barrel | B12: 21.81 | C12: Each | D12: 141.56 | E12: List Price | F12: US Dollar | G12: N0-00010 | H12: 16748
A13: Flow Cell Body | B13: 114.06 | C13: Each | D13: 268.71 | E13: List Price | F13: US Dollar | G13: N0-00011 | H13: 16752
A14: Flow Cell Exit | B14: 20.57 | C14: Each | D14: 53.73 | E14: List Price | F14: US Dollar | G14: N0-00012 | H14: 16753
A15: SIT Base | B15: 12.69 | C15: Each | D15: 38.07 | E15: List Price | F15: US Dollar | G15: N0-00013 | H15: 16754
A16: Red Prism Block | B16: 11.49 | C16: Each | D16: 57.09 | E16: List Price | F16: US Dollar | G16: N0-00014 | H16: 16757
... A1085: 0.07" EPDM O-ring Cord Stock | B1085: 0.27 | C1085: Foot | D1085: 0.02461 | E1085: List Price | F1085: US Dollar | G1085: N4-00095 | H1085: 75631
A1087: MMC 9616K11
A1088: O-RING, AS568A-159, EPDM 70 DURO | B1088: 12.16 | C1088: Each | D1088: 0.48 | E1088: List Price | F1088: US Dollar | G1088: N4-00100 | H1088: 15287
A1089: 1/4-28 x 1/8 FEMALE Luer BARB PANEL MT | B1089: 0.57 | C1089: Each | D1089: 1.52 | E1089: List Price | F1089: US Dollar | G1089: N4-00104 | H1089: 15319
A1090: Tee Tube Fitting with Classic Series Barbs, 1/8" (3.2 | B1090: 1.04 | C1090: Each | D1090: 2.67 | E1090: List Price | F1090: US Dollar | G1090: N4-00105 | H1090: 15339
A1091: Aria 1/32" Ferrule for PEEK Tubing in PMI Kit | B1091: 2 | C1091: Each | D1091: 9.21 | E1091: List Price | F1091: US Dollar | G1091: N4-00106 | H1091: 15342
A1092: ALMOND BULKHEAD 1/8" | B1092: 7.91 | C1092: Each | D1092: 41.91 | E1092: List Price | F1092: US Dollar | G1092: N4-00107 | H1092: 15370
A1093: FEMALE 1/4 NPT COLDER | B1093: 6.47 | C1093: Each | D1093: 29.43 | E1093: List Price | F1093: US Dollar | G1093: N4-00112 | H1093: 15373
A1094: ALMOND MALE COLDER 1/8" | B1094: 5.51 | C1094: Each | D1094: 18.33 | E1094: List Price | F1094: US Dollar | G1094: N4-00114 | H1094: 15376
A1095: ORG MALE COLDER 1/8" | B1095: 7.05 | C1095: Each | D1095: 18.33 | E1095: List Price | F1095: US Dollar | G1095: N4-00116 | H1095: 49212
A1096: SHEATH LEVEL SENSOR CAP | B1096: 3.56 | C1096: Each | D1096: 46.68 | E1096: List Price | F1096: US Dollar | G1096: N4-00118 | H1096: 15485
A1097: NC FLOAT SWITCH Brown Wires | B1097: 35.74 | C1097: Each | D1097: 94.74 | E1097: List Price | F1097: US Dollar | G1097: N4-00120 | H1097: 15490
A1098: Pressure Transducer Athena/Rainbow | B1098: 48.99 | C1098: Each | D1098: 183 | E1098: List Price | F1098: US Dollar | G1098: N4-00122 | H1098: 15567
A1099: 4L Tank | B1099: 126.9 | C1099: Each | D1099: 137.22 | E1099: List Price | F1099: US Dollar | G1099: N4-00124 | H1099: 15568
... A2662: RYV Upgrade (Monthly) | B2662: 0 | C2662: Each | D2662: 525 | E2662: List Price | F2662: US Dollar | G2662: N9-90097 | H2662: 105652
A2663: OQ Package (2PM visits) | B2663: 0 | D2663: 10500 | E2663: List Price | F2663: US Dollar | G2663: N9-90099 | H2663: 68075
A2664: OQ Package (All service visits) | B2664: 0 | D2664: 15750 | E2664: List Price | F2664: US Dollar | G2664: N9-90100 | H2664: 68076
A2665: IQ/OQ | B2665: 0 | D2665: 10500 | E2665: List Price | F2665: US Dollar | G2665: N9-90101 | H2665: 22353
A2666: Annual Surcharge | B2666: 0 | C2666: Each | D2666: 1313 | E2666: List Price | F2666: US Dollar | G2666: N9-90102 | H2666: 65838
A2667: Quarterly Surcharge | B2667: 0 | C2667: Each | D2667: 2625 | E2667: List Price | F2667: US Dollar | G2667: N9-90103 | H2667: 65839
A2668: BSL3/4 Surcharge | B2668: 0 | C2668: Each | D2668: 10500 | E2668: List Price | F2668: US Dollar | G2668: N9-90104 | H2668: 109579
A2669: BSL3/4 Surcharge | B2669: 0 | C2669: Each | D2669: 10000 | E2669: List Price | F2669: US Dollar | G2669: N9-90104-INA | H2669: 65840
A2670: Priority Response | B2670: 0 | C2670: Each | D2670: 1575 | E2670: List Price | F2670: US Dollar | G2670: N9-90105 | H2670: 20180
A2671: Cytek Spectral Cytometry Additional Training Provisions | B2671: 0 | C2671: Each | D2671: 5516 | E2671: List Price | F2671: US Dollar | G2671: N9-90106 | H2671: 68301
A2672: Cytek Spectral Cytometry Online Lecture Series | B2672: 0 | C2672: Each | D2672: 2350 | E2672: List Price | F2672: US Dollar | G2672: N9-90107 | H2672: 68302
A2673: Cytek Spectral Cytometry On-site Instrument Training | B2673: 0 | C2673: Each | D2673: 7164 | E2673: List Price | F2673: US Dollar | G2673: N9-90108 | H2673: 68303
A2674: Cytek Spectral Cytometry Remote Instrument Training | B2674: 0 | C2674: Each | D2674: 2271 | E2674: List Price | F2674: US Dollar | G2674: N9-90109 | H2674: 68304
A2675: Aurora-CS 3- Laser (B/R/V) - Value | B2675: 0 | C2675: Each | D2675: 24134 | E2675: List Price | F2675: US Dollar | G2675: N9-90110 | H2675: 109580
A2676: Aurora-CS 3- Laser (B/R/V) - Value | B2676: 0 | C2676: Each | D2676: 20688 | E2676: List Price | F2676: US Dollar | G2676: N9-90110-INA | H2676: 105451
A2677: Aurora-CS 4- Laser (B/R/V/YG) - Value | B2677: 0 | C2677: Each | D2677: 29090 | E2677: List Price | F2677: US Dollar | G2677: N9-90112 | H2677: 109581
... A2898: ImageStream Preventative Maintenance Service | B2898: 0 | C2898: Each | D2898: 9800 | E2898: List Price | F2898: US Dollar | G2898: PM-IMAGESTREAM | H2898: 166565
B2899: 0 | C2899: Each | D2899: 642.9 | E2899: List Price | F2899: US Dollar | G2899: Pre-amp Board Test Station | H2899: 43870
A2900: cFluor®R720 anti-Mouse/Human CD44 (IM7), 25 tests (Kit Only) | B2900: 0.34 | C2900: Each | D2900: 95 | E2900: List Price | F2900: US Dollar | G2900: R6-20030 | H2900: 258013
A2901: cFluor™ B520 Anti-Human CD3 (SK7) | B2901: 1 | C2901: Each | D2901: 416 | E2901: List Price | F2901: US Dollar | G2901: R7-11001 | H2901: 127838
A2902: Fluorochrome: cFluor™ B520
A2903: Clone: SK7
A2904: Isotype: IgG1, kappa
A2905: Host: Mouse
A2906: Size: 100 Tests
A2907: cFluor™ B520 Anti-Human CD3 (SK7) | B2907: 0.85 | C2907: Each | D2907: 167 | E2907: List Price | F2907: US Dollar | G2907: R7-11002 | H2907: 127839
A2908: Size: 25 Tests
A2909: cFluor BYG781 Anti-Human CD4 (SK3) | B2909: 0.91 | C2909: Each | D2909: 564 | E2909: List Price | F2909: US Dollar | G2909: R7-11003 | H2909: 127832
A2910: Fluorochrome: cFluor BYG781
A2911: Clone: SK3
A2912: cFluor BYG781 Anti-Human CD4 (SK3) | B2912: 0.85 | C2912: Each | D2912: 162 | E2912: List Price | F2912: US Dollar | G2912: R7-11004 | H2912: 127833
A2913: cFluor R780 Anti-Human CD8 (SK1) | B2913: 1 | C2913: Each | D2913: 513 | E2913: List Price | F2913: US Dollar | G2913: R7-11005 | H2913: 128126
A2914: Fluorochrome: cFluor R780
A2915: Clone: SK1
A2916: cFluor R780 Anti-Human CD8 (SK1) | B2916: 0.85 | C2916: Each | D2916: 146 | E2916: List Price | F2916: US Dollar | G2916: R7-11006 | H2916: 127837
A2917: cFluor™ BYG575 Anti-Human CD16 (3G8) | B2917: 1 | C2917: Each | D2917: 405 | E2917: List Price | F2917: US Dollar | G2917: R7-11007 | H2917: 128226
A2918: Fluorochrome: cFluor™ BYG575
A2919: Clone: 3G8
A2920: cFluor™ BYG575 Anti-Human CD16 (3G8) | B2920: 0.85 | C2920: Each | D2920: 108 | E2920: List Price | F2920: US Dollar | G2920: R7-11008 | H2920: 128227
A2921: cFluor™ B690 Anti-Human CD45 (2D1) | B2921: 1 | C2921: Each | D2921: 443 | E2921: List Price | F2921: US Dollar | G2921: R7-11009 | H2921: 127728
A2922: Fluorochrome: cFluor™ B690
A2923: Clone: 2D1
A2924: cFluor™ B690 Anti-Human CD45 (2D1) | B2924: 0.85 | C2924: Each | D2924: 119 | E2924: List Price | F2924: US Dollar | G2924: R7-11010 | H2924: 127843
A2925: cFluor™ V547 Anti-Human CD45 (HI30) | B2925: 2.42 | C2925: Each | D2925: 564 | E2925: List Price | F2925: US Dollar | G2925: R7-11011 | H2925: 127844
A2926: Fluorochrome: cFluor™ V547
A2927: Clone: HI30
A2928: Size 100 Tests
A2929: cFluor™ V547 Anti-Human CD45 (HI30) | B2929: 1.22 | C2929: Each | D2929: 226 | E2929: List Price | F2929: US Dollar | G2929: R7-11012 | H2929: 128325
A2930: Size 25 Tests
A2931: cFluor BYG610 Anti-Human CD8 (SK1) | B2931: 1 | C2931: Each | D2931: 513 | E2931: List Price | F2931: US Dollar | G2931: R7-11013 | H2931: 127929
A2932: Fluorochrome: cFluor BYG610
A2933: cFluor BYG610 Anti-Human CD8 (SK1) | B2933: 0.85 | C2933: Each | D2933: 146 | E2933: List Price | F2933: US Dollar | G2933: R7-11014 | H2933: 127727
A2934: cFluor™ BYG575 Anti-Human CD56 (5.1H11) | B2934: 1 | C2934: Each | D2934: 445 | E2934: List Price | F2934: US Dollar | G2934: R7-11015 | H2934: 127930
A2935: Clone: 5.1H11
A2936: cFluor™ BYG575 Anti-Human CD56 (5.1H11) | B2936: 0.85 | C2936: Each | D2936: 179 | E2936: List Price | F2936: US Dollar | G2936: R7-11016 | H2936: 128326
A2937: cFluor® BYG610 Anti-Human CD33 (WM53) Format: cFluor® BYG610 Clone: WM53 Isotype: Mouse IgG1, kappa Size: 100Tests | B2937: 220.24 | C2937: Each | D2937: 368 | E2937: List Price | F2937: US Dollar | G2937: R7-11021 | H2937: 127845
A2938: cFluor® BYG610 Anti-Human CD33 (WM53) Format: cFluor® BYG610 Clone: WM53 Isotype: Mouse IgG1, kappa Size: 25 Tests | B2938: 56.7 | C2938: Each | D2938: 148 | E2938: List Price | F2938: US Dollar | G2938: R7-11022 | H2938: 128130
A2939: cFluor® BYG610 Anti-Human CD117 (104D2) | B2939: 42.73 | C2939: Each | D2939: 368 | E2939: List Price | F2939: US Dollar | G2939: R7-11023 | H2939: 128131
A2940: Fluorochrome: cFluor® BYG610
A2941: Clone: 104D2
A2942: Isotype: Mouse IgG1, kappa
A2943: cFluor® BYG610 Anti-Human CD117 (104D2) | B2943: 11.48 | C2943: Each | D2943: 148 | E2943: List Price | F2943: US Dollar | G2943: R7-11024 | H2943: 127846
A2944: cFluor™ B548 Anti-Human CD15 (HI98) | B2944: 11.81 | C2944: Each | D2944: 488 | E2944: List Price | F2944: US Dollar | G2944: R7-11025 | H2944: 128334
A2945: Fluorochrome: cFluor™ B548
A2946: Clone: HI98
A2947: Isotype: IgM, κ
A2948: cFluor™ B548 Anti-Human CD15 (HI98) | B2948: 3.6 | C2948: Each | D2948: 191 | E2948: List Price | F2948: US Dollar | G2948: R7-11026 | H2948: 128335
A2949: cFluor B515 Anti-Human CD4 (SK3) | B2949: 1.1 | C2949: Each | D2949: 416 | E2949: List Price | F2949: US Dollar | G2949: R7-11027 | H2949: 127725
A2950: Fluorochrome: cFluor B515
A2951: Isotype: IgG1, κ
...

Sheet Cytek Service Quoting Old
C2: ='FSE Input Old'!A3 -> Brad Ballard | F2: ="QUOTE#: "&'FSE Input Old'!$D$3&" "&'FSE Input Old'!$B$3 -> #REF!
C3: ='FSE Input Old'!C3 -> #REF!
C4: ='FSE Input Old'!E3 -> #REF!
C7: Item | D7: Description | E7: Product Number | F7: Qty | G7: List Price | H7: Net Price | I7: Ext. Price
C8: =IF(D8="", "", "1") -> 1 | D8: =IF('FSE Input Old'!A7<>"", 'FSE Input Old'!A7, IF('FSE Input Old'!E7<>"", 'FSE Input Old'!E7, "")) -> On-Site Support (2 days) | E8: =IF('FSE Input Old'!B7<>"", 'FSE Input Old'!B7, IF('FSE Input Old'!F7<>"", 'FSE Input Old'!F7, "")) -> 60020 | F8: =IF(ISBLANK('FSE Input Old'!D7),"",'FSE Input Old'!D7) -> 1 | G8: =IF('FSE Input Old'!C7<>"", 'FSE Input Old'!C7, IF('FSE Input Old'!G7<>"", 'FSE Input Old'!G7, "")) -> 7571 | H8: =IF(G8="", "", IF(ISNUMBER(SEARCH("on-site", D8)), G8, IF(ISNUMBER(SEARCH("basic", 'FSE Input Old'!F$3)), G8*0.9, IF(ISNUMBER(SEARCH("value", 'FSE Input Old'!F$3)), G8-750, "") ) ) ) -> 7571 | I8: =IF(G8="","",H8*F8) -> 7571
C9: =IF(D9="", "", "2") -> 2 | D9: =IF('FSE Input Old'!A8<>"", 'FSE Input Old'!A8, IF('FSE Input Old'!E8<>"", 'FSE Input Old'!E8, "")) -> guava eacyCyte HT Preventative Maintenance | E9: =IF('FSE Input Old'!B8<>"", 'FSE Input Old'!B8, IF('FSE Input Old'!F8<>"", 'FSE Input Old'!F8, "")) -> PM-EASYCYTE-HT | F9: =IF(ISBLANK('FSE Input Old'!D8),"",'FSE Input Old'!D8) -> 1 | G9: =IF('FSE Input Old'!C8<>"", 'FSE Input Old'!C8, IF('FSE Input Old'!G8<>"", 'FSE Input Old'!G8, "")) -> 4814 | H9: =IF(G9="", "", IF(ISNUMBER(SEARCH("on-site", D9)), G9, IF(ISNUMBER(SEARCH("basic", 'FSE Input Old'!F$3)), G9*0.9, IF(ISNUMBER(SEARCH("value", 'FSE Input Old'!F$3)), G9-750, "") ) ) ) | I9: =IF(G9="","",H9*F9) -> #VALUE!
C10: =IF(D10="", "", "3") -> 3 | D10: =IF('FSE Input Old'!A9<>"", 'FSE Input Old'!A9, IF('FSE Input Old'!E9<>"", 'FSE Input Old'!E9, "")) -> Sheath Filter, Rainbow | E10: =IF('FSE Input Old'!B9<>"", 'FSE Input Old'!B9, IF('FSE Input Old'!F9<>"", 'FSE Input Old'!F9, "")) -> N4-00025 | F10: =IF(ISBLANK('FSE Input Old'!D9),"",'FSE Input Old'!D9) -> 1 | G10: =IF('FSE Input Old'!C9<>"", 'FSE Input Old'!C9, IF('FSE Input Old'!G9<>"", 'FSE Input Old'!G9, "")) -> 192.45 | H10: =IF(G10="", "", IF(ISNUMBER(SEARCH("on-site", D10)), G10, IF(ISNUMBER(SEARCH("basic", 'FSE Input Old'!F$3)), G10*0.9, IF(ISNUMBER(SEARCH("value", 'FSE Input Old'!F$3)), G10-750, "") ) ) ) | I10: =IF(G10="","",H10*F10) -> #VALUE!
C11: =IF(D11="", "", "4") | D11: =IF('FSE Input Old'!A10<>"", 'FSE Input Old'!A10, IF('FSE Input Old'!E10<>"", 'FSE Input Old'!E10, "")) | E11: =IF('FSE Input Old'!B10<>"", 'FSE Input Old'!B10, IF('FSE Input Old'!F10<>"", 'FSE Input Old'!F10, "")) | F11: =IF(ISBLANK('FSE Input Old'!D10),"",'FSE Input Old'!D10) | G11: =IF('FSE Input Old'!C10<>"", 'FSE Input Old'!C10, IF('FSE Input Old'!G10<>"", 'FSE Input Old'!G10, "")) | H11: =IF(G11="", "", IF(ISNUMBER(SEARCH("on-site", D11)), G11, IF(ISNUMBER(SEARCH("basic", 'FSE Input Old'!F$3)), G11*0.9, IF(ISNUMBER(SEARCH("value", 'FSE Input Old'!F$3)), G11-750, "") ) ) ) | I11: =IF(G11="","",H11*F11)
C13: Shipping & Handling Estimate
C14: Total | I14: =SUM(I15,I8:I11) -> #VALUE!
G49: ="QUOTE#: "&'FSE Input Old'!$D$3&" "&'FSE Input Old'!$B$3 -> #REF!
G101: ="QUOTE#: "&'FSE Input Old'!$D$3&" "&'FSE Input Old'!$B$3 -> #REF!
G153: ="QUOTE#: "&'FSE Input Old'!$D$3&" "&'FSE Input Old'!$B$3 -> #REF!

Sheet FSE Input Old
A1: CUSTOMER INFORMATION
A2: Name of customer requesting service/part: | B2: Instrument SN: | C2: Facility name: | D2: Shortened Facility name (ex. BCH): | E2: Facility Address: | F2: Contract type:
A3: Brad Ballard | B3: U0286 | C3: =VLOOKUP(B3,#REF!,2,FALSE) -> #REF! | D3: =VLOOKUP(C3,#REF!,2,FALSE) -> #REF! | E3: =VLOOKUP(B3,#REF!,19,FALSE) -> #REF! | F3: =VLOOKUP(B3,#REF!,9,FALSE) -> #REF!
A5: SERVICE TYPE / PART NAME
A6: Service Type/ Part Name | B6: Service Type/Part Number | C6: Service Type/ Part Price | D6: Quantity | E6: Service Type / Part Name (if not listed) | F6: Service Type Part Number (if not listed) | G6: Price of Service Type / Part (if not listed)
A7: On-Site Support (2 days) | B7: =IF(A7="","",VLOOKUP(A7,'Pricing Data'!A$2:H5436,7,FALSE)) -> 60020 | C7: =IF(A7="","",VLOOKUP(A7,'Pricing Data'!A2:H5436,4,FALSE)) -> 7571 | D7: 1
A8: guava eacyCyte HT Preventative Maintenance | B8: =IF(A8="","",VLOOKUP(A8,'Pricing Data'!A$2:H5437,7,FALSE)) -> PM-EASYCYTE-HT | C8: =IF(A8="","",VLOOKUP(A8,'Pricing Data'!A2:H5437,4,FALSE)) -> 4814 | D8: 1
A9: Sheath Filter, Rainbow | B9: =IF(A9="","",VLOOKUP(A9,'Pricing Data'!A$2:H5438,7,FALSE)) -> N4-00025 | C9: =IF(A9="","",VLOOKUP(A9,'Pricing Data'!A2:H5438,4,FALSE)) -> 192.45 | D9: 1
B10: =IF(A10="","",VLOOKUP(A10,'Pricing Data'!A2:H5439,7,FALSE)) | C10: =IF(A10="","",VLOOKUP(A10,'Pricing Data'!A2:H5439,4,FALSE))
B18: Name of customer requesting service/part: | C18: Brad Ballard | E18: SERVICE TYPE / PART NAME | F18: Service Type/ Part Name | G18: On-Site Support (2 days) | H18: guava eacyCyte HT Preventative Maintenance | I18: Sheath Filter, Rainbow
B19: Instrument SN: | C19: U0286 | F19: Service Type/Part Number | G19: =IF(G18="","",VLOOKUP(G18,'Pricing Data'!$B18:HAB25,7,FALSE)) -> #N/A | H19: =IF(H18="","",VLOOKUP(H18,'Pricing Data'!$B18:HAC25,7,FALSE)) -> #N/A | I19: =IF(I18="","",VLOOKUP(I18,'Pricing Data'!$B18:HAD25,7,FALSE)) -> #N/A | J19: =IF(J18="","",VLOOKUP(J18,'Pricing Data'!B18:HAE25,7,FALSE))
B20: Facility name: | C20: =VLOOKUP(C19,#REF!,2,FALSE) -> #REF! | F20: Service Type/ Part Price | G20: =IF(G18="","",VLOOKUP(G18,'Pricing Data'!B18:HAB25,4,FALSE)) -> #N/A | H20: =IF(H18="","",VLOOKUP(H18,'Pricing Data'!B18:HAC25,4,FALSE)) -> #N/A | I20: =IF(I18="","",VLOOKUP(I18,'Pricing Data'!B18:HAD25,4,FALSE)) -> #N/A | J20: =IF(J18="","",VLOOKUP(J18,'Pricing Data'!B18:HAE25,4,FALSE))
B21: Shortened Facility name (ex. BCH): | C21: =VLOOKUP(C20,#REF!,2,FALSE) -> #REF! | F21: Quantity | G21: 1 | H21: 1 | I21: 1
B22: Facility Address: | C22: =VLOOKUP(C19,#REF!,19,FALSE) -> #REF! | F22: Service Type / Part Name (if not listed)
B23: Contract type: | C23: =VLOOKUP(C19,#REF!,9,FALSE) -> #REF! | F23: Service Type Part Number (if not listed)
F24: Price of Service Type / Part (if not listed)
A32: SERVICE TYPE/PART NAME - SERVICE QUOTE
B33: Part 1 | C33: Part 2 | D33: Part 3 | E33: Part 4
A34: Service Type/ Part Name | B34: On-Site Support (2 days) | C34: guava eacyCyte HT Preventative Maintenance | D34: Sheath Filter, Rainbow
A35: Service Type/Part Number | B35: =IF(B34="","",VLOOKUP(B34,'Pricing Data'!$B31:GZX38,7,FALSE)) -> #N/A | C35: =IF(C34="","",VLOOKUP(C34,'Pricing Data'!$B31:GZY38,7,FALSE)) -> #N/A | D35: =IF(D34="","",VLOOKUP(D34,'Pricing Data'!$B31:GZZ38,7,FALSE)) -> #N/A | E35: =IF(E34="","",VLOOKUP(E34,'Pricing Data'!#REF!,7,FALSE))
A36: Service Type/ Part Price | B36: =IF(B34="","",VLOOKUP(B34,'Pricing Data'!#REF!,4,FALSE)) -> #REF! | C36: =IF(C34="","",VLOOKUP(C34,'Pricing Data'!#REF!,4,FALSE)) -> #REF! | D36: =IF(D34="","",VLOOKUP(D34,'Pricing Data'!#REF!,4,FALSE)) -> #REF! | E36: =IF(E34="","",VLOOKUP(E34,'Pricing Data'!#REF!,4,FALSE))
A37: Quantity | B37: 1 | C37: 1 | D37: 1
A38: Service Type / Part Name (if not listed)
A39: Service Type Part Number (if not listed)
A40: Price of Service Type / Part (if not listed)
