Workbook

Sheet Admin
A2: Relocation fee???
H7: basic/PMI Bronze has 10% discount
A8: Service and Parts | B8: TS email, contract matters for discount
A9: Move | B9: contract doesn't matter
A10: Parts ONLY | B10: orders email, contract matters for discount
H11: protection on cells - turn into API
C15: Contract pricing - service
C16: Contract | D16: ='FSE Input'!B13 -> 0 | E16: labor? | F16: cost | G16: premium contract | H16: 20% discount | I16: 10% dicsount | J16: final price
C17: part 1 | D17: =IF('FSE Input'!B17<>"",'FSE Input'!B17,IF('FSE Input'!B21<>"",'FSE Input'!B21,"")) -> On-Site Support (2 days) | E17: =IF(OR(ISNUMBER(SEARCH("site",D17)),ISNUMBER(SEARCH("service",D17)),ISNUMBER(SEARCH("support",D17))),"Yes","No") -> Yes | F17: =IF('FSE Input'!B19<>"",'FSE Input'!B19,IF('FSE Input'!B23<>"",'FSE Input'!B23,"")) -> 7571 | G17: =IF(E17="Yes", F17, IF(OR($D$16="Premium", $D$16="Gold", ISNUMBER(SEARCH("COMPLET",$D$16))), F17, "")) -> 7571 | H17: =IF(E17="Yes", F17, IF(OR($D$16="VALUE", $D$16="Silver", ISNUMBER(SEARCH("INTERMED",$D$16))), F17*0.8, "")) -> 7571 | I17: =IF(E17="Yes", F17, IF(OR($D$16="PMI", $D$16="Bronze", ISNUMBER(SEARCH("BASIC",$D$16))), F17*0.9, "")) -> 7571 | J17: =IF(E17="Yes", F17, IF(OR($D$16="Premium", $D$16="Gold", ISNUMBER(SEARCH("COMPLET",$D$16))), F17, IF(OR($D$16="VALUE", $D$16="Silver", ISNUMBER(SEARCH("INTERMED",$D$16))), F17*0.8, IF(OR($D$16="PMI", $D$16="Bronze", ISNUMBER(SEARCH("BASIC",$D$16))), F17*0.9, "" ) ) ) ) -> 7571
C18: part 2 | D18: =IF('FSE Input'!B25<>"",'FSE Input'!B25,IF('FSE Input'!B29<>"",'FSE Input'!B29,"")) | E18: =IF(OR(ISNUMBER(SEARCH("site",D18)),ISNUMBER(SEARCH("service",D18)),ISNUMBER(SEARCH("support",D18))),"Yes","No") -> No | F18: =IF('FSE Input'!B27<>"",'FSE Input'!B27,IF('FSE Input'!B31<>"",'FSE Input'!B31,"")) | G18: =IF(E18="Yes", F18, IF(OR($D$16="Premium", $D$16="Gold", ISNUMBER(SEARCH("COMPLET",$D$16))), F18, "")) | H18: =IF(E18="Yes", F18, IF(OR($D$16="VALUE", $D$16="Silver", ISNUMBER(SEARCH("INTERMED",$D$16))), F18*0.8, "")) | I18: =IF(E18="Yes", F18, IF(OR($D$16="PMI", $D$16="Bronze", ISNUMBER(SEARCH("BASIC",$D$16))), F18*0.9, "")) | J18: =IF(E18="Yes", F18, IF(OR($D$16="Premium", $D$16="Gold", ISNUMBER(SEARCH("COMPLET",$D$16))), F18, IF(OR($D$16="VALUE", $D$16="Silver", ISNUMBER(SEARCH("INTERMED",$D$16))), F18*0.8, IF(OR($D$16="PMI", $D$16="Bronze", ISNUMBER(SEARCH("BASIC",$D$16))), F18*0.9, "" ) ) ) )
C19: part 3 | D19: =IF('FSE Input'!B33<>"",'FSE Input'!B33,IF('FSE Input'!B37<>"",'FSE Input'!B37,"")) | E19: =IF(OR(ISNUMBER(SEARCH("site",D19)),ISNUMBER(SEARCH("service",D19)),ISNUMBER(SEARCH("support",D19))),"Yes","No") -> No | F19: =IF('FSE Input'!B35<>"",'FSE Input'!B35,IF('FSE Input'!B39<>"",'FSE Input'!B39,"")) | G19: =IF(E19="Yes", F19, IF(OR($D$16="Premium", $D$16="Gold", ISNUMBER(SEARCH("COMPLET",$D$16))), F19, "")) | H19: =IF(E19="Yes", "", IF(OR($D$16="VALUE", $D$16="Silver", ISNUMBER(SEARCH("INTERMED",$D$16))), F19*0.8, "")) | I19: =IF(E19="Yes", F19, IF(OR($D$16="PMI", $D$16="Bronze", ISNUMBER(SEARCH("BASIC",$D$16))), F19*0.9, "")) | J19: =IF(E19="Yes", F19, IF(OR($D$16="Premium", $D$16="Gold", ISNUMBER(SEARCH("COMPLET",$D$16))), F19, IF(OR($D$16="VALUE", $D$16="Silver", ISNUMBER(SEARCH("INTERMED",$D$16))), F19*0.8, IF(OR($D$16="PMI", $D$16="Bronze", ISNUMBER(SEARCH("BASIC",$D$16))), F19*0.9, "" ) ) ) )
C20: part 4 | D20: =IF('FSE Input'!B41<>"",'FSE Input'!B41,IF('FSE Input'!B45<>"",'FSE Input'!B45,"")) | E20: =IF(OR(ISNUMBER(SEARCH("site",D20)),ISNUMBER(SEARCH("service",D20)),ISNUMBER(SEARCH("support",D20))),"Yes","No") -> No | F20: =IF('FSE Input'!B43<>"",'FSE Input'!B43,IF('FSE Input'!B47<>"",'FSE Input'!B47,"")) | G20: =IF(E20="Yes", F20, IF(OR($D$16="Premium", $D$16="Gold", ISNUMBER(SEARCH("COMPLET",$D$16))), F20, "")) | H20: =IF(E20="Yes", F20, IF(OR($D$16="VALUE", $D$16="Silver", ISNUMBER(SEARCH("INTERMED",$D$16))), F20*0.8, "")) | I20: =IF(E20="Yes", F20, IF(OR($D$16="PMI", $D$16="Bronze", ISNUMBER(SEARCH("BASIC",$D$16))), F20*0.9, "")) | J20: =IF(E20="Yes", F20, IF(OR($D$16="Premium", $D$16="Gold", ISNUMBER(SEARCH("COMPLET",$D$16))), F20, IF(OR($D$16="VALUE", $D$16="Silver", ISNUMBER(SEARCH("INTERMED",$D$16))), F20*0.8, IF(OR($D$16="PMI", $D$16="Bronze", ISNUMBER(SEARCH("BASIC",$D$16))), F20*0.9, "" ) ) ) )
C22: contract pricing - parts
C23: contract | D23: ='FSE Input'!E13 -> Premium | E23: labor? | F23: cost | G23: premium | H23: 20% discount | I23: 10% discount | J23: final price
C24: part 1 | D24: =IF('FSE Input'!E17<>"",'FSE Input'!E17,IF('FSE Input'!E21<>"",'FSE Input'!E21,"")) -> On-Site Support (2 days) | E24: =IF(OR(ISNUMBER(SEARCH("site",D24)),ISNUMBER(SEARCH("service",D24)),ISNUMBER(SEARCH("support",D24))),"Yes","No") -> Yes | F24: =IF('FSE Input'!E19<>"",'FSE Input'!E19,IF('FSE Input'!E23<>"",'FSE Input'!E23,"")) -> 7571 | G24: =IF(E24="Yes", F24, IF(OR($D$23="Premium", $D$23="Gold", ISNUMBER(SEARCH("COMPLET",$D$23))), F24, "")) -> 7571 | H24: =IF(E24="Yes", F24, IF(OR($D$23="VALUE", $D$23="Silver", ISNUMBER(SEARCH("INTERMED",$D$23))), F24*0.8, "")) -> 7571 | I24: =IF(E24="Yes", F24, IF(OR($D$23="PMI", $D$23="Bronze", ISNUMBER(SEARCH("BASIC",$D$23))), F24*0.9, "")) -> 7571 | J24: =IF(E24="Yes", F24, IF(OR($D$23="Premium", $D$23="Gold", ISNUMBER(SEARCH("COMPLET",$D$23))), F24, IF(OR($D$23="VALUE", $D$23="Silver", ISNUMBER(SEARCH("INTERMED",$D$23))), F24*0.8, IF(OR($D$23="PMI", $D$23="Bronze", ISNUMBER(SEARCH("BASIC",$D$23))), F24*0.9, "" ) ) ) ) -> 7571
C25: part 2 | D25: =IF('FSE Input'!E25<>"",'FSE Input'!E25,IF('FSE Input'!E29<>"",'FSE Input'!E29,"")) -> Flow Cell Body | E25: =IF(OR(ISNUMBER(SEARCH("site",D25)),ISNUMBER(SEARCH("service",D25)),ISNUMBER(SEARCH("support",D25))),"Yes","No") -> No | F25: =IF('FSE Input'!E27<>"",'FSE Input'!E27,IF('FSE Input'!E31<>"",'FSE Input'!E31,"")) -> 268.71 | G25: =IF(E25="Yes", F25, IF(OR($D$23="Premium", $D$16="Gold", ISNUMBER(SEARCH("COMPLET",$D$23))), F25, "")) -> 268.71 | H25: =IF(E25="Yes", F25, IF(OR($D$23="VALUE", $D$23="Silver", ISNUMBER(SEARCH("INTERMED",$D$23))), F25*0.8, "")) | I25: =IF(E25="Yes", F25, IF(OR($D$16="PMI", $D$16="Bronze", ISNUMBER(SEARCH("BASIC",$D$16))), F25*0.9, "")) | J25: =IF(E25="Yes", F25, IF(OR($D$23="Premium", $D$23="Gold", ISNUMBER(SEARCH("COMPLET",$D$23))), F25, IF(OR($D$23="VALUE", $D$23="Silver", ISNUMBER(SEARCH("INTERMED",$D$23))), F25*0.8, IF(OR($D$23="PMI", $D$23="Bronze", ISNUMBER(SEARCH("BASIC",$D$23))), F25*0.9, "" ) ) ) ) -> 268.71
C26: part 3 | D26: =IF('FSE Input'!E33<>"",'FSE Input'!E33,IF('FSE Input'!E37<>"",'FSE Input'!E37,"")) -> Mounting Plate | E26: =IF(OR(ISNUMBER(SEARCH("site",D26)),ISNUMBER(SEARCH("service",D26)),ISNUMBER(SEARCH("support",D26))),"Yes","No") -> No | F26: =IF('FSE Input'!E35<>"",'FSE Input'!E35,IF('FSE Input'!E39<>"",'FSE Input'!E39,"")) -> 7.76 | G26: =IF(E26="Yes", F26, IF(OR($D$23="Premium", $D$23="Gold", ISNUMBER(SEARCH("COMPLET",$D$23))), F26, "")) -> 7.76 | H26: =IF(E26="Yes", "", IF(OR($D$23="VALUE", $D$23="Silver", ISNUMBER(SEARCH("INTERMED",$D$23))), F26*0.8, "")) | I26: =IF(E26="Yes", F26, IF(OR($D$16="PMI", $D$16="Bronze", ISNUMBER(SEARCH("BASIC",$D$16))), F26*0.9, "")) | J26: =IF(E26="Yes", F26, IF(OR($D$23="Premium", $D$23="Gold", ISNUMBER(SEARCH("COMPLET",$D$23))), F26, IF(OR($D$23="VALUE", $D23="Silver", ISNUMBER(SEARCH("INTERMED",$D$23))), F26*0.8, IF(OR($D$23="PMI", $D$23="Bronze", ISNUMBER(SEARCH("BASIC",$D$23))), F26*0.9, "" ) ) ) ) -> 7.76
C27: part 4 | D27: =IF('FSE Input'!E41<>"",'FSE Input'!E41,IF('FSE Input'!E45<>"",'FSE Input'!E45,"")) -> generator | E27: =IF(OR(ISNUMBER(SEARCH("site",D27)),ISNUMBER(SEARCH("service",D27)),ISNUMBER(SEARCH("support",D27))),"Yes","No") -> No | F27: =IF('FSE Input'!E43<>"",'FSE Input'!E43,IF('FSE Input'!E47<>"",'FSE Input'!E47,"")) -> 800 | G27: =IF(E27="Yes", F27, IF(OR($D$23="Premium", $D$23="Gold", ISNUMBER(SEARCH("COMPLET",$D$23))), F27, "")) -> 800 | H27: =IF(E27="Yes", F27, IF(OR($D$23="VALUE", $D$23="Silver", ISNUMBER(SEARCH("INTERMED",$D$23))), F27*0.8, "")) | I27: =IF(E27="Yes", F27, IF(OR($D$16="PMI", $D$16="Bronze", ISNUMBER(SEARCH("BASIC",$D$16))), F27*0.9, "")) | J27: =IF(E27="Yes", F27, IF(OR($D$23="Premium", $D$23="Gold", ISNUMBER(SEARCH("COMPLET",$D$23))), F27, IF(OR($D$23="VALUE", $D$23="Silver", ISNUMBER(SEARCH("INTERMED",$D$23))), F27*0.8, IF(OR($D$23="PMI", $D$23="Bronze", ISNUMBER(SEARCH("BASIC",$D$23))), F27*0.9, "" ) ) ) ) -> 800
D34: need to include the if not listed here | F34: test if all work for if not listed
D35: note
D36: add a little popup that says if the contract is value, amke sure this is not the customer's first repair if so no quote needed
D37: how to do pricing? which cell has numbers? or combine everything into one

Sheet FSE Input
A1: What are you quoting?
A2: Service and Parts
A6: Use "Cytek Service Quoting" Tab to print quote | D6: Use "Cytek Parts Quoting" Tab to print quote
A7: CUSTOMER INFORMATION - SERVICE QUOTE | D7: Customer information - Parts Quote
A8: Name of customer requesting service/part: | B8: Alyssa Sanfillipo | D8: Name of customer requesting service/part: | E8: Mike Waring
A9: Instrument SN: | B9: R0732 | D9: Instrument SN: | E9: U1399
A10: Facility name: | B10: =VLOOKUP(B9,'Asset Data'!C$2:U$3586,2,FALSE) -> abata THERAPEUTICS | D10: Facility name: | E10: =VLOOKUP(E9,'Asset Data'!C$2:U$3586,2,FALSE) -> Ragon Institute of MGH MIT and Harvard
A11: Shortened Facility name | B11: =VLOOKUP(B10,'Asset Data'!D1:E3586,2,FALSE) -> ABATA | D11: Shortened Facility name | E11: =VLOOKUP(E10,'Asset Data'!D1:E3586,2,FALSE) -> RGON
A12: Facility Address: | B12: =VLOOKUP(B9,'Asset Data'!C2:U3586,19,FALSE) -> 100 Forge Street (2nd Floor), Watertown, Massachusetts 02472, U.S. | D12: Facility Address: | E12: =VLOOKUP(E9,'Asset Data'!C2:U3586,19,FALSE) -> Ragon Institute of MGH MIT and Harvard - 600 Main St, Cambridge, Massachusetts 02139, U.S.
A13: Contract type: | B13: =VLOOKUP(B9,'Asset Data'!C2:U3586,9,FALSE) -> 0 | D13: Contract type: | E13: =VLOOKUP(E9,'Asset Data'!C2:U3586,9,FALSE) -> Premium
A15: SERVICE TYPE/PART NAME - SERVICE QUOTE | D15: SERVICE TYPE/PART NAME - PARTS QUOTE
A16: PART 1 | D16: PART 1
A17: Service Type/ Part Name | B17: On-Site Support (2 days) | D17: Service Type/ Part Name | E17: On-Site Support (2 days)
A18: Service Type/Part Number | B18: =IF(B17="","",VLOOKUP(B17,'Pricing Data'!A$2:H5436,7,FALSE)) -> 60020 | D18: Service Type/Part Number | E18: =IF(E17="","",VLOOKUP(E17,'Pricing Data'!A$2:H5436,7,FALSE)) -> 60020
A19: Service Type/ Part Price | B19: =IF(B17="","",VLOOKUP(B17,'Pricing Data'!A$2:H5436,4,FALSE)) -> 7571 | D19: Service Type/ Part Price | E19: =IF(E17="","",VLOOKUP(E17,'Pricing Data'!A$2:H5436,4,FALSE)) -> 7571
A20: Quantity | B20: 1 | D20: Quantity | E20: 1
A21: Service Type / Part Name (if not listed) | D21: Service Type / Part Name (if not listed)
A22: Service Type Part Number (if not listed) | D22: Service Type Part Number (if not listed)
A23: Price of Service Type / Part (if not listed) | D23: Price of Service Type / Part (if not listed)
A24: PART 2 | D24: PART 2
A25: Service Type/ Part Name | D25: Service Type/ Part Name | E25: Flow Cell Body
A26: Service Type/Part Number | B26: =IF(B25="","",VLOOKUP(B25,'Pricing Data'!A$2:H5436,7,FALSE)) | D26: Service Type/Part Number | E26: =IF(E25="","",VLOOKUP(E25,'Pricing Data'!A$2:H5444,7,FALSE)) -> N0-00011
A27: Service Type/ Part Price | B27: =IF(B25="","",VLOOKUP(B25,'Pricing Data'!A$2:H5436,4,FALSE)) | D27: Service Type/ Part Price | E27: =IF(E25="","",VLOOKUP(E25,'Pricing Data'!A$2:H5444,4,FALSE)) -> 268.71
A28: Quantity | D28: Quantity | E28: 1
A29: Service Type / Part Name (if not listed) | D29: Service Type / Part Name (if not listed)
A30: Service Type Part Number (if not listed) | D30: Service Type Part Number (if not listed)
A31: Price of Service Type / Part (if not listed) | D31: Price of Service Type / Part (if not listed)
A32: PART 3 | D32: PART 3
A33: Service Type/ Part Name | D33: Service Type/ Part Name | E33: Mounting Plate
A34: Service Type/Part Number | B34: =IF(B33="","",VLOOKUP(B33,'Pricing Data'!A$2:H5436,7,FALSE)) | D34: Service Type/Part Number | E34: =IF(E33="","",VLOOKUP(E33,'Pricing Data'!A$2:H5452,7,FALSE)) -> N0-00002
A35: Service Type/ Part Price | B35: =IF(B33="","",VLOOKUP(B33,'Pricing Data'!A$2:H5436,4,FALSE)) | D35: Service Type/ Part Price | E35: =IF(E33="","",VLOOKUP(E33,'Pricing Data'!A$2:H5452,4,FALSE)) -> 7.76
A36: Quantity | D36: Quantity | E36: 1
A37: Service Type / Part Name (if not listed) | D37: Service Type / Part Name (if not listed)
A38: Service Type Part Number (if not listed) | D38: Service Type Part Number (if not listed)
A39: Price of Service Type / Part (if not listed) | D39: Price of Service Type / Part (if not listed)
A40: PART 4 | D40: PART 4
A41: Service Type/ Part Name | D41: Service Type/ Part Name
A42: Service Type/Part Number | B42: =IF(B41="","",VLOOKUP(B41,'Pricing Data'!A$2:H5436,7,FALSE)) | D42: Service Type/Part Number | E42: =IF(E41="","",VLOOKUP(E41,'Pricing Data'!A$2:H5460,7,FALSE))
A43: Service Type/ Part Price | B43: =IF(B41="","",VLOOKUP(B41,'Pricing Data'!A$2:H5436,4,FALSE)) | D43: Service Type/ Part Price | E43: =IF(E41="","",VLOOKUP(E41,'Pricing Data'!A$2:H5460,4,FALSE))
A44: Quantity | D44: Quantity | E44: 1
A45: Service Type / Part Name (if not listed) | D45: Service Type / Part Name (if not listed) | E45: generator
A46: Service Type Part Number (if not listed) | D46: Service Type Part Number (if not listed) | E46: u1093
A47: Price of Service Type / Part (if not listed) | D47: Price of Service Type / Part (if not listed) | E47: 800

Sheet Cytek Service Quoting
C2: ='FSE Input'!B8 -> Alyssa Sanfillipo | F2: ="QUOTE#: "&'FSE Input'!$B$11&" "&'FSE Input'!$B$9 -> QUOTE#: ABATA R0732
C3: ='FSE Input'!B10 -> abata THERAPEUTICS
C4: ='FSE Input'!B12 -> 100 Forge Street (2nd Floor), Watertown, Massachusetts 02472, U.S.
C7: Item | D7: Description | E7: Product Number | F7: Qty | G7: List Price | H7: Net Price | I7: Ext. Price
C8: =IF(D8="", "", "1") -> 1 | D8: =IF('FSE Input'!B17<>"", 'FSE Input'!B17, IF('FSE Input'!B21<>"", 'FSE Input'!B21, "")) -> On-Site Support (2 days) | E8: =IF('FSE Input'!B18<>"", 'FSE Input'!B18, IF('FSE Input'!B22<>"", 'FSE Input'!B22, "")) -> 60020 | F8: =IF(ISBLANK('FSE Input'!B20),"",'FSE Input'!B20) -> 1 | G8: =IF('FSE Input'!B19<>"", 'FSE Input'!B19, IF('FSE Input'!B23<>"", 'FSE Input'!B23, "")) -> 7571 | H8: =IF(Admin!D17<>"",Admin!J17,"") -> 7571 | I8: =IF(G8="","",H8*F8) -> 7571
C9: =IF(D9="", "", "2") | D9: =IF('FSE Input'!B25<>"", 'FSE Input'!B25, IF('FSE Input'!B29<>"", 'FSE Input'!B29, "")) | E9: =IF('FSE Input'!B26<>"", 'FSE Input'!B26, IF('FSE Input'!B30<>"", 'FSE Input'!B30, "")) | F9: =IF(ISBLANK('FSE Input'!B28),"",'FSE Input'!B28) | G9: =IF('FSE Input'!B27<>"", 'FSE Input'!B27, IF('FSE Input'!B31<>"", 'FSE Input'!B31, "")) | H9: =IF(Admin!D18<>"",Admin!J18,"") | I9: =IF(G9="","",H9*F9)
C10: =IF(D10="", "", "3") | D10: =IF('FSE Input'!B33<>"", 'FSE Input'!B33, IF('FSE Input'!B37<>"", 'FSE Input'!B37, "")) | E10: =IF('FSE Input'!B34<>"", 'FSE Input'!B34, IF('FSE Input'!B38<>"", 'FSE Input'!B38, "")) | F10: =IF(ISBLANK('FSE Input'!B36),"",'FSE Input'!B36) | G10: =IF('FSE Input'!B35<>"", 'FSE Input'!B35, IF('FSE Input'!B39<>"", 'FSE Input'!B39, "")) | H10: =IF(Admin!D19<>"",Admin!J19,"") | I10: =IF(G10="","",H10*F10)
C11: =IF(D11="", "", "4") | D11: =IF('FSE Input'!B41<>"", 'FSE Input'!B41, IF('FSE Input'!B45<>"", 'FSE Input'!B45, "")) | E11: =IF('FSE Input'!B42<>"", 'FSE Input'!B42, IF('FSE Input'!B46<>"", 'FSE Input'!B46, "")) | F11: =IF(ISBLANK('FSE Input'!B44),"",'FSE Input'!B44) | G11: =IF('FSE Input'!B43<>"", 'FSE Input'!B43, IF('FSE Input'!B47<>"", 'FSE Input'!B47, "")) | H11: =IF(Admin!D20<>"",Admin!J20,"") | I11: =IF(G11="","",H11*F11)
C13: Shipping & Handling Estimate
C14: Total | I14: =SUM(I15,I8:I11) -> 7571
D16: Pre-Inspection/Recertification
G101: ="QUOTE#: "&'FSE Input Old'!$D$3&" "&'FSE Input Old'!$B$3 -> QUOTE#: MSU U0286
G153: ="QUOTE#: "&'FSE Input Old'!$D$3&" "&'FSE Input Old'!$B$3 -> QUOTE#: MSU U0286

Sheet Cytek Parts Quoting
C2: ='FSE Input'!E8 -> Mike Waring | F2: ="QUOTE#: "&'FSE Input'!$E$11&" "&'FSE Input'!$E$9 -> QUOTE#: RGON U1399
C3: ='FSE Input'!E10 -> Ragon Institute of MGH MIT and Harvard
C4: ='FSE Input'!E12 -> Ragon Institute of MGH MIT and Harvard - 600 Main St, Cambridge, Massachusetts 02139, U.S.
C7: Item | D7: Description | E7: Product Number | F7: Qty | G7: List Price | H7: Net Price | I7: Ext. Price
C8: =IF(D8="", "", "1") -> 1 | D8: =IF('FSE Input'!E17<>"", 'FSE Input'!E17, IF('FSE Input'!E21<>"", 'FSE Input'!E21, "")) -> On-Site Support (2 days) | E8: =IF('FSE Input'!E18<>"", 'FSE Input'!E18, IF('FSE Input'!E22<>"", 'FSE Input'!E22, "")) -> 60020 | F8: =IF(ISBLANK('FSE Input'!E20),"",'FSE Input'!E20) -> 1 | G8: =IF('FSE Input'!E19<>"", 'FSE Input'!E19, IF('FSE Input'!E23<>"", 'FSE Input'!E23, "")) -> 7571 | H8: =IF(Admin!D24<>"",Admin!J24,"") -> 7571 | I8: =IF(G8="","",H8*F8) -> 7571
C9: =IF(D9="", "", "2") -> 2 | D9: =IF('FSE Input'!E25<>"", 'FSE Input'!E25, IF('FSE Input'!E29<>"", 'FSE Input'!E29, "")) -> Flow Cell Body | E9: =IF('FSE Input'!E26<>"", 'FSE Input'!E26, IF('FSE Input'!E30<>"", 'FSE Input'!E30, "")) -> N0-00011 | F9: =IF(ISBLANK('FSE Input'!E28),"",'FSE Input'!E28) -> 1 | G9: =IF('FSE Input'!E27<>"", 'FSE Input'!E27, IF('FSE Input'!E31<>"", 'FSE Input'!E31, "")) -> 268.71 | H9: =IF(Admin!D25<>"",Admin!J25,"") -> 268.71 | I9: =IF(G9="","",H9*F9) -> 268.71
C10: =IF(D10="", "", "3") -> 3 | D10: =IF('FSE Input'!E33<>"", 'FSE Input'!E33, IF('FSE Input'!E37<>"", 'FSE Input'!E37, "")) -> Mounting Plate | E10: =IF('FSE Input'!E34<>"", 'FSE Input'!E34, IF('FSE Input'!E38<>"", 'FSE Input'!E38, "")) -> N0-00002 | F10: =IF(ISBLANK('FSE Input'!E36),"",'FSE Input'!E36) -> 1 | G10: =IF('FSE Input'!E35<>"", 'FSE Input'!E35, IF('FSE Input'!E39<>"", 'FSE Input'!E39, "")) -> 7.76 | H10: =IF(Admin!D26<>"",Admin!J26,"") -> 7.76 | I10: =IF(G10="","",H10*F10) -> 7.76
C11: =IF(D11="", "", "4") -> 4 | D11: =IF('FSE Input'!E41<>"", 'FSE Input'!E41, IF('FSE Input'!E45<>"", 'FSE Input'!E45, "")) -> generator | E11: =IF('FSE Input'!E42<>"", 'FSE Input'!E42, IF('FSE Input'!E46<>"", 'FSE Input'!E46, "")) -> u1093 | F11: =IF(ISBLANK('FSE Input'!E44),"",'FSE Input'!E44) -> 1 | G11: =IF('FSE Input'!E43<>"", 'FSE Input'!E43, IF('FSE Input'!E47<>"", 'FSE Input'!E47, "")) -> 800 | H11: =IF(Admin!D27<>"",Admin!J27,"") -> 800 | I11: =IF(G11="","",H11*F11) -> 800
C13: Shipping & Handling Estimate
C14: Total | I14: =SUM(I15,I8:I11) -> 8647.47
G49: ="QUOTE#: "&'FSE Input Old'!$D$3&" "&'FSE Input Old'!$B$3 -> QUOTE#: MSU U0286
G101: ="QUOTE#: "&'FSE Input Old'!$D$3&" "&'FSE Input Old'!$B$3 -> QUOTE#: MSU U0286
G153: ="QUOTE#: "&'FSE Input Old'!$D$3&" "&'FSE Input Old'!$B$3 -> QUOTE#: MSU U0286

Sheet Asset Data
A1: Region | B1: Country | C1: Asset Name | D1: Account: Account Name | E1: shortened facility name | F1: Service Territory: Name | G1: Primary Service Technician | H1: Primary FAS | I1: Account Owner | J1: Synced Contract: Contract Number | K1: Synced Contract: Contract Type | L1: Synced Contract: Status | M1: Product: Product Name | N1: Contact: Full Name | O1: Contact: Email | P1: Special Handling Indicator | Q1: Street | R1: City | S1: State and Zip code | T1: Country | U1: Installed Address
A2: North America | B2: U.S. | C2: 8470060264 | D2: 10X GENOMICS | E2: 10XGEN | F2: US-Oakland | H2: Jonathan Paw | I2: Karen Young | J2: 00030294 | K2: SLA-EC-COMPLETE | L2: Activated | M2: Guava easyCyte 6HT-2L | N2: JAZY CHEUNG | O2: jazy.cheung@10xgenomics.com | Q2: 6230 STONERIDGE MALL RD | R2: PLEASANTON | S2: California 94588 | T2: U.S. | U2: =_xlfn.TEXTJOIN(", ", TRUE, Q2, R2, S2, T2) -> 6230 STONERIDGE MALL RD, PLEASANTON, California 94588, U.S.
A3: North America | B3: U.S. | C3: 8470060262 | D3: 10X GENOMICS | E3: 10XGEN | F3: US-Oakland | H3: Jonathan Paw | I3: Karen Young | J3: 00036340 | K3: SLA-EC-COMPLETE | L3: Activated | M3: Guava easyCyte 6HT-2L | N3: Taylor Wyatt | O3: taylor.wyatt@10xgenomics.com | Q3: 5500 Stoneridge Mall Rd | R3: PLEASANTON | S3: California 94588 | T3: U.S. | U3: =_xlfn.TEXTJOIN(", ", TRUE, Q3, R3, S3, T3) -> 5500 Stoneridge Mall Rd, PLEASANTON, California 94588, U.S.
A4: North America | B4: U.S. | C4: 8470060146 | D4: 10X GENOMICS | E4: 10XGEN | F4: US-Oakland | H4: Jonathan Paw | I4: Karen Young | J4: 00032541 | K4: SLA-EC-COMPLETE | L4: Expired | M4: Guava easyCyte 6HT-2L | N4: EMIL ANTHONY GIMENEZ | O4: emilanthony.gimenez@10xgenomics.com | Q4: 5500 Stoneridge Mall Rd | R4: PLEASANTON | S4: California 94588 | T4: U.S. | U4: =_xlfn.TEXTJOIN(", ", TRUE, Q4, R4, S4, T4) -> 5500 Stoneridge Mall Rd, PLEASANTON, California 94588, U.S.
A5: North America | B5: U.S. | C5: 6735148243 | D5: 1GLOBE HEALTH INSTITUTE | E5: GHI | F5: US-Boston | H5: Mark Stottlemyer | I5: Lindsay Albert | M5: Guava easyCyte 8HT | N5: AMANDA PIAZZA | O5: apiazza1@1globe-usa.com | Q5: 333 PROVIDENCE HWY | R5: NORWOOD | S5: Massachusetts 02062 | T5: U.S. | U5: =_xlfn.TEXTJOIN(", ", TRUE, Q5, R5, S5, T5) -> 333 PROVIDENCE HWY, NORWOOD, Massachusetts 02062, U.S.
A6: North America | B6: U.S. | C6: 8470050267 | D6: 23ANDME INC | E6: 23&M3 | F6: US-San Francisco | H6: Jonathan Paw | I6: Alexandra Dudschus | M6: Guava easyCyte 5HT, Boxed Instrument | Q6: 349 OYSTER POINT BLVD | R6: SOUTH SAN FRANCISCO | S6: California 94080 | T6: U.S. | U6: =_xlfn.TEXTJOIN(", ", TRUE, Q6, R6, S6, T6) -> 349 OYSTER POINT BLVD, SOUTH SAN FRANCISCO, California 94080, U.S.
A7: North America | B7: U.S. | C7: EC221246C1 | D7: 3M | E7: 3M | F7: US-Minneapolis | H7: Joel Crespo | I7: Gregory Kleedtke | M7: Guava easyCyte 6HT-2L | N7: EMILY JULIK | O7: ejulik@mmm.com | Q7: 3M CTR BLDG 201-2E-232 | R7: MAPLEWOOD | S7: Minnesota 55144 | T7: U.S. | U7: =_xlfn.TEXTJOIN(", ", TRUE, Q7, R7, S7, T7) -> 3M CTR BLDG 201-2E-232, MAPLEWOOD, Minnesota 55144, U.S.
A8: North America | B8: U.S. | C8: EC213486C1 | D8: 3M | E8: 3M | F8: US-Minneapolis | H8: Joel Crespo | I8: Gregory Kleedtke | M8: Guava easyCyte 6HT-2L | N8: NARINA STEPANOVA | O8: nstepanova@mmm.com | Q8: 3M CTR BLDG 201 | R8: MAPLEWOOD | S8: Minnesota 55114 | T8: U.S. | U8: =_xlfn.TEXTJOIN(", ", TRUE, Q8, R8, S8, T8) -> 3M CTR BLDG 201, MAPLEWOOD, Minnesota 55114, U.S.
A9: North America | B9: U.S. | C9: 6735146222 | D9: 3M | E9: 3M | F9: US-Minneapolis | H9: Joel Crespo | I9: Gregory Kleedtke | M9: Guava easyCyte 6HT-2L | N9: JANA NINKOVIC | O9: jninkovic@mmm.com | Q9: 3M CTR BLDG 201-2E-232 | R9: Maplewood | S9: Minnesota 55144 | T9: U.S. | U9: =_xlfn.TEXTJOIN(", ", TRUE, Q9, R9, S9, T9) -> 3M CTR BLDG 201-2E-232, Maplewood, Minnesota 55144, U.S.
A10: North America | B10: U.S. | C10: R1329 | D10: 92Bio Inc | E10: 92BIO | F10: US-Oakland | G10: Stacy Stocki | H10: Carol Oxford | I10: Leland Brasher | J10: 00034590 | K10: Premium | L10: Activated | M10: Cytek Aurora 3 Laser V/B/R - (38 + 3 Channel) | N10: Heather Maecker | O10: hmaecker@ancorabiotech.com | Q10: 1190 Zephyr Ave, Ste A | R10: Hayward | S10: California 94544 | T10: U.S. | U10: =_xlfn.TEXTJOIN(", ", TRUE, Q10, R10, S10, T10) -> 1190 Zephyr Ave, Ste A, Hayward, California 94544, U.S.
A11: North America | B11: U.S. | C11: EC220396F1 | D11: A M TODD | E11: AMTD | I11: Leland Brasher | M11: Guava easyCyte 11HT | N11: JIE LIU | O11: jie.liu@adm.com | Q11: 4091 W 11TH AVE STE E | R11: EUGENE | S11: Oregon 97402 | T11: U.S. | U11: =_xlfn.TEXTJOIN(", ", TRUE, Q11, R11, S11, T11) -> 4091 W 11TH AVE STE E, EUGENE, Oregon 97402, U.S.
A12: North America | B12: U.S. | C12: V0792 | D12: AAT Bioquest | E12: AATB | F12: US-Oakland | G12: Stacy Stocki | H12: Jonathan Paw | I12: Leland Brasher | J12: 00033158 | K12: PMI | L12: Expired | M12: Cytek Aurora 4 Laser UV/V/B/R/ (54 + 3 Channel) | N12: Helen Qin Zhao | O12: helen@aatbio.com | Q12: 5775 W. Las Positas Boulevard | R12: Pleasanton | S12: California 94588 | T12: U.S. | U12: =_xlfn.TEXTJOIN(", ", TRUE, Q12, R12, S12, T12) -> 5775 W. Las Positas Boulevard, Pleasanton, California 94588, U.S.
A13: North America | B13: U.S. | C13: R0732 | D13: abata THERAPEUTICS | E13: ABATA | F13: US-Boston | G13: James Martin | H13: Mark Stottlemyer | I13: Lindsay Albert | M13: Cytek Aurora 3 Laser V/B/R - (38 + 3 Channel) | N13: Juliana Barrios | O13: jbarrios@abatatx.com | Q13: 100 Forge Street (2nd Floor) | R13: Watertown | S13: Massachusetts 02472 | T13: U.S. | U13: =_xlfn.TEXTJOIN(", ", TRUE, Q13, R13, S13, T13) -> 100 Forge Street (2nd Floor), Watertown, Massachusetts 02472, U.S.
A14: North America | B14: U.S. | C14: N0416 | D14: AbboMax, Inc. | E14: ABMX | F14: US-Sacramento | G14: Aldrin Aragon | H14: Jonathan Paw | I14: Leland Brasher | J14: 00012556 | K14: Warranty | L14: Expired | M14: Cytek Northern Lights 3000 V/B/R - (38 + 3 channel) | N14: Kelly Y. Zhou M.D., Ph.D | O14: kellyz@abbomax.com | Q14: 2528 Qume Drive | R14: San Jose | S14: California 95131 | T14: U.S. | U14: =_xlfn.TEXTJOIN(", ", TRUE, Q14, R14, S14, T14) -> 2528 Qume Drive, San Jose, California 95131, U.S.
A15: North America | B15: U.S. | C15: U1611 | D15: AbbVie Inc - AbbVie Bioresearch Center | E15: ABBV | F15: US-Boston | G15: Ilya Permyakov | H15: Mark Stottlemyer | I15: Lindsay Albert | J15: 00036473 | K15: Premium | L15: Activated | M15: Cytek Aurora 5 Laser UV/V/B/YG/R (64 + 3 Channel) | N15: Bit Na Kang | O15: bitna.kang@abbvie.com | Q15: 100 Research Drive | R15: Worcester | S15: Massachusetts 01605 | T15: U.S. | U15: =_xlfn.TEXTJOIN(", ", TRUE, Q15, R15, S15, T15) -> 100 Research Drive, Worcester, Massachusetts 01605, U.S.
A16: North America | B16: U.S. | C16: U1309 | D16: AbbVie Inc - AbbVie Bioresearch Center | E16: ABBV | F16: US-Boston | G16: Ilya Permyakov | H16: Mark Stottlemyer | I16: Lindsay Albert | J16: 00035224 | K16: Premium | L16: Activated | M16: Cytek Aurora 5 Laser UV/V/B/YG/R (64 + 3 Channel) | N16: Zachary Niziolek | O16: zachary.niziolek@abbvie.com | Q16: 100 Research Drive | R16: Worcester | S16: Massachusetts 01605 | T16: U.S. | U16: =_xlfn.TEXTJOIN(", ", TRUE, Q16, R16, S16, T16) -> 100 Research Drive, Worcester, Massachusetts 01605, U.S.
A17: North America | B17: U.S. | C17: ISX440 | D17: AbbVie Inc - AbbVie Bioresearch Center | E17: ABBV | F17: US-Boston | G17: Ilya Permyakov | H17: Mark Stottlemyer | I17: Lindsay Albert | J17: 00035298 | K17: SLA-ISXMKII-COMPLETE | L17: Activated | M17: ImageStreamX MkII Instrument | N17: AXEL HERNANDEZ | O17: axel.hernandezjr@abbvie.com | Q17: 381 PLANTATION ST BIOTECH 5 | R17: WORCESTER | S17: Massachusetts 01605 | T17: U.S. | U17: =_xlfn.TEXTJOIN(", ", TRUE, Q17, R17, S17, T17) -> 381 PLANTATION ST BIOTECH 5, WORCESTER, Massachusetts 01605, U.S.
A18: North America | C18: XF1002 | D18: AbbVie Inc - AbbVie Bioresearch Center | E18: ABBV | G18: Ilya Permyakov | H18: Mark Stottlemyer | I18: Lindsay Albert | J18: 00036967 | K18: Premium | L18: Activated | M18: Cytek Aurora? Evo 5L UV/V/B/YG/R | N18: Bit Na Kang | O18: bitna.kang@abbvie.com | Q18: Precision Medicine Immunology Translational Research 830 Winter Street | R18: Waltham | S18: Massachusetts 02451 | T18: U.S. | U18: =_xlfn.TEXTJOIN(", ", TRUE, Q18, R18, S18, T18) -> Precision Medicine Immunology Translational Research 830 Winter Street, Waltham, Massachusetts 02451, U.S.
A19: North America | C19: U1741 | D19: AbbVie Inc - AbbVie Bioresearch Center | E19: ABBV | F19: US-Boston | G19: Ilya Permyakov | H19: Mark Stottlemyer | I19: Lindsay Albert | J19: 00035019 | K19: Warranty | L19: Activated | M19: Cytek Aurora 5 Laser UV/V/B/YG/R (64 + 3 Channel) | N19: Woojong Lee | O19: woojong.lee@abbvie.com | Q19: 830 Winter Street | R19: Waltham | S19: Massachusetts 02451 | T19: U.S. | U19: =_xlfn.TEXTJOIN(", ", TRUE, Q19, R19, S19, T19) -> 830 Winter Street, Waltham, Massachusetts 02451, U.S.
A20: North America | C20: SM1012 | D20: AbbVie Inc - AbbVie Bioresearch Center | E20: ABBV | F20: US-Boston | G20: Ilya Permyakov | H20: Mark Stottlemyer | I20: Lindsay Albert | J20: 00036524 | K20: Warranty | L20: Activated | M20: Cytek Northern Lights 3000 V/B/R - (38 + 3 channel) | N20: Racheal Akwii | O20: racheal.akwii@abbvie.com | Q20: 381 Plantation Street | R20: Worcester | S20: Massachusetts 01605 | T20: U.S. | U20: =_xlfn.TEXTJOIN(", ", TRUE, Q20, R20, S20, T20) -> 381 Plantation Street, Worcester, Massachusetts 01605, U.S.
A21: North America | C21: NM1678 | D21: AbbVie Inc - AbbVie Bioresearch Center | E21: ABBV | F21: US-Boston | G21: Ilya Permyakov | H21: Mark Stottlemyer | I21: Lindsay Albert | J21: 00036242 | K21: Warranty | L21: Activated | M21: Cytek Northern Lights 3000 V/B/R - (38 + 3 channel) | N21: Cassie Liu | O21: cassie.liu@abbvie.com | Q21: 100 Research Drive | R21: Worcester | S21: Massachusetts 01605 | T21: U.S. | U21: =_xlfn.TEXTJOIN(", ", TRUE, Q21, R21, S21, T21) -> 100 Research Drive, Worcester, Massachusetts 01605, U.S.
A22: North America | B22: U.S. | C22: Y0090 | D22: AbbVie Inc - Bay Area | E22: ABBV | F22: US-San Francisco | G22: Aldrin Aragon | H22: Jonathan Paw | I22: Leland Brasher | J22: 00035179 | K22: Premium | L22: Activated | M22: Cytek Aurora 5 Laser UV/V/B/YG/R (64 + 3 Channel) | N22: Devika Ashok | O22: devika.ashok@abbvie.com | Q22: 05-580 1000 Gateway Blvd | R22: South San Francisco | S22: California 94080 | T22: U.S. | U22: =_xlfn.TEXTJOIN(", ", TRUE, Q22, R22, S22, T22) -> 05-580 1000 Gateway Blvd, South San Francisco, California 94080, U.S.
A23: North America | B23: U.S. | C23: V0350 | D23: AbbVie Inc - Bay Area | E23: ABBV | F23: US-San Francisco | G23: Aldrin Aragon | H23: Jonathan Paw | I23: Leland Brasher | J23: 00035175 | K23: Value | L23: Activated | M23: Cytek Aurora 4 Laser UV/V/B/R/ (54 + 3 Channel) | N23: Claudia Bispo | O23: claudia.bispo@abbvie.com | Q23: 1000 Gateway Blvd Lab 03-590 | R23: South San Francisco | S23: California 94080 | T23: U.S. | U23: =_xlfn.TEXTJOIN(", ", TRUE, Q23, R23, S23, T23) -> 1000 Gateway Blvd Lab 03-590, South San Francisco, California 94080, U.S.
A24: North America | B24: U.S. | C24: V0252 | D24: AbbVie Inc - Bay Area | E24: ABBV | F24: US-San Francisco | G24: Aldrin Aragon | H24: Jonathan Paw | I24: Leland Brasher | J24: 00035177 | K24: Premium | L24: Activated | M24: Cytek Aurora 5 Laser UV/V/B/YG/R (64 + 3 Channel) | N24: Devika Ashok | O24: devika.ashok@abbvie.com | Q24: 1000 Gateway Blvd 5th Floor room#580 | R24: South San Francisco | S24: California 94080 | T24: U.S. | U24: =_xlfn.TEXTJOIN(", ", TRUE, Q24, R24, S24, T24) -> 1000 Gateway Blvd 5th Floor room#580, South San Francisco, California 94080, U.S.
A25: North America | B25: U.S. | C25: U1148 | D25: AbbVie Inc - Bay Area | E25: ABBV | F25: US-San Francisco | G25: Aldrin Aragon | H25: Jonathan Paw | I25: Leland Brasher | J25: 00035180 | K25: Value | L25: Activated | M25: Cytek Aurora 5 Laser UV/V/B/YG/R (64 + 3 Channel) | N25: Claudia Bispo | O25: claudia.bispo@abbvie.com | Q25: 1000 Gateway Blvd Claudia Bispo Lab 03-590 | R25: South San Francisco | S25: California 94080 | T25: U.S. | U25: =_xlfn.TEXTJOIN(", ", TRUE, Q25, R25, S25, T25) -> 1000 Gateway Blvd Claudia Bispo Lab 03-590, South San Francisco, California 94080, U.S.
A26: North America | B26: U.S. | C26: U0557 | D26: AbbVie Inc - Bay Area | E26: ABBV | F26: US-San Francisco | G26: Aldrin Aragon | H26: Jonathan Paw | I26: Leland Brasher | J26: 00035178 | K26: Premium | L26: Activated | M26: Cytek Aurora 5 Laser UV/V/B/YG/R (64 + 3 Channel) | N26: Claudia Bispo | O26: claudia.bispo@abbvie.com | Q26: 03-590Â 1000 Gateway Blvd | R26: South San Francisco | S26: California 94080 | T26: U.S. | U26: =_xlfn.TEXTJOIN(", ", TRUE, Q26, R26, S26, T26) -> 03-590Â 1000 Gateway Blvd, South San Francisco, California 94080, U.S.
A27: North America | C27: 6735145217 | D27: AbbVie Inc - Bay Area | E27: ABBV | G27: Aldrin Aragon | H27: Jonathan Paw | I27: Leland Brasher | N27: JASON BAKER | O27: jason.baker@abbvie.com | U27: =_xlfn.TEXTJOIN(", ", TRUE, Q27, R27, S27, T27)
A28: North America | B28: U.S. | C28: U1372 | D28: AbbVie Inc - Cambridge MA | E28: ABBV | F28: US-Boston | G28: Ilya Permyakov | H28: Mark Stottlemyer | I28: Lindsay Albert | J28: 00036234 | K28: Warranty | L28: Activated | M28: Cytek Aurora 5 Laser UV/V/B/YG/R (64 + 3 Channel) - REFURBISHED | N28: Abeer Obaid | O28: abeer.obaid@abbvie.com | P28: Demo unit U1372 sold to AbbVie Inc in Cambridge, MA. SO.HQ42438 | Q28: 200 Sidney Street | R28: Cambridge | S28: Massachusetts 02139 | T28: U.S. | U28: =_xlfn.TEXTJOIN(", ", TRUE, Q28, R28, S28, T28) -> 200 Sidney Street, Cambridge, Massachusetts 02139, U.S.
A29: North America | B29: U.S. | C29: U0656 | D29: AbbVie Inc - Cambridge MA | E29: ABBV | F29: US-Boston | G29: Ilya Permyakov | H29: Mark Stottlemyer | I29: Lindsay Albert | J29: 00036385 | K29: Premium | L29: Activated | M29: Cytek Aurora 5 Laser UV/V/B/YG/R (64 + 3 Channel) | N29: Nick Hawrylciw | O29: nick.hawrylciw@thermofisher.com | Q29: 40 Guest St | R29: Boston | S29: Massachusetts 02135 | T29: U.S. | U29: =_xlfn.TEXTJOIN(", ", TRUE, Q29, R29, S29, T29) -> 40 Guest St, Boston, Massachusetts 02135, U.S.
A30: North America | B30: U.S. | C30: S0103 | D30: AbbVie Inc - Cambridge MA | E30: ABBV | F30: US-Boston | G30: Ilya Permyakov | H30: Mark Stottlemyer | I30: Lindsay Albert | J30: 00036384 | K30: Premium | L30: Activated | M30: Cytek Aurora-CS 5L System | N30: Khadir Raddassi | O30: khadir.raddassi@abbvie.com | Q30: 40 Guest Street | R30: Boston | S30: Massachusetts 02135 | T30: U.S. | U30: =_xlfn.TEXTJOIN(", ", TRUE, Q30, R30, S30, T30) -> 40 Guest Street, Boston, Massachusetts 02135, U.S.
A31: North America | B31: U.S. | C31: ISX725 | D31: AbbVie Inc - Irvine CA | E31: ABBV | F31: US-Burbank | H31: Aric Bitton | I31: Robert Thacker | J31: 00029470 | K31: SLA-ISXMKII-COMPLETE | L31: Expired | M31: ImageStreamX MkII Instrument | N31: Rob Thacker | O31: rthacker@cytekbio.com | Q31: 2525 Dupont Ave | R31: Irvine | S31: California 92612 | T31: U.S. | U31: =_xlfn.TEXTJOIN(", ", TRUE, Q31, R31, S31, T31) -> 2525 Dupont Ave, Irvine, California 92612, U.S.
A32: North America | B32: U.S. | C32: U1130 | D32: AbbVie Inc - North Chicago | E32: ABBV | F32: US-Chicago | G32: Maria Stanslaski | H32: Joel Crespo | I32: Karen Young | J32: 00035010 | K32: Premium | L32: Activated | M32: Cytek Aurora 5 Laser UV/V/B/YG/R (64 + 3 Channel) | N32: Marion Refici | O32: marion.refici@abbvie.com | Q32: GPRD Stockroom AP9 1 North Waukegan Rd | R32: North Chicago | S32: Illinois 60064 | T32: U.S. | U32: =_xlfn.TEXTJOIN(", ", TRUE, Q32, R32, S32, T32) -> GPRD Stockroom AP9 1 North Waukegan Rd, North Chicago, Illinois 60064, U.S.
A33: North America | B33: U.S. | C33: U0647 | D33: AbbVie Inc - North Chicago | E33: ABBV | F33: US-Chicago | G33: Maria Stanslaski | H33: Joel Crespo | I33: Karen Young | J33: 00035238 | K33: Premium | L33: Activated | M33: Cytek Aurora 5 Laser UV/V/B/YG/R (64 + 3 Channel) | N33: Ryan Duggan | O33: ryan.duggan@abbvie.com | Q33: 1 North Waukegan Road AP9 â?? 1 â?? 1601 | R33: North Chicago | S33: Illinois 60064 | T33: U.S. | U33: =_xlfn.TEXTJOIN(", ", TRUE, Q33, R33, S33, T33) -> 1 North Waukegan Road AP9 â?? 1 â?? 1601, North Chicago, Illinois 60064, U.S.
A34: North America | B34: U.S. | C34: U0277 | D34: AbbVie Inc - North Chicago | E34: ABBV | F34: US-Chicago | G34: Maria Stanslaski | H34: Joel Crespo | I34: Karen Young | J34: 00036186 | K34: Premium | L34: Activated | M34: Cytek Aurora 5 Laser UV/V/B/YG/R (64 + 3 Channel) | N34: Loren Lasko | O34: loren.lasko@abbvie.com | Q34: 1 North Waukegan Rd,Rm AP9-1601 | R34: North Chicago | S34: Illinois 60064 | T34: U.S. | U34: =_xlfn.TEXTJOIN(", ", TRUE, Q34, R34, S34, T34) -> 1 North Waukegan Rd,Rm AP9-1601, North Chicago, Illinois 60064, U.S.
A35: North America | B35: U.S. | C35: ISX433 | D35: AbbVie Inc - North Chicago | E35: ABBV | F35: US-Chicago | G35: Maria Stanslaski | H35: Joel Crespo | I35: Karen Young | J35: 00035244 | K35: SLA-ISXMKII-COMPLETE | L35: Activated | M35: ImageStreamX MkII Instrument | N35: SHAMIM KHAJA | O35: shamim.khaja@abbvie.com | Q35: 1 N Waukegan Rd Bldg AP9 Lab 1310 | R35: North Chicago | S35: Illinois 60044 | T35: U.S. | U35: =_xlfn.TEXTJOIN(", ", TRUE, Q35, R35, S35, T35) -> 1 N Waukegan Rd Bldg AP9 Lab 1310, North Chicago, Illinois 60044, U.S.
A36: North America | B36: U.S. | C36: N0136 | D36: ABBVsion | E36: ABVIS | F36: US-Sacramento | G36: Aldrin Aragon | H36: Jonathan Paw | I36: Leland Brasher | J36: 00013234 | K36: Premium | L36: Expired | M36: Cytek Northern Lights 3000 V/B/R - (38 + 3 channel) | Q36: 2528 Qume Drive, Suite 12 | R36: San Jose | S36: California 95131 | T36: U.S. | U36: =_xlfn.TEXTJOIN(", ", TRUE, Q36, R36, S36, T36) -> 2528 Qume Drive, Suite 12, San Jose, California 95131, U.S.
A37: North America | B37: U.S. | C37: EC213266H1 | D37: Abcam Inc | E37: ABCM | F37: US-Boston | H37: Mark Stottlemyer | I37: Lindsay Albert | J37: 00026318 | K37: SLA-EC-INTERMED | L37: Expired | M37: Guava easyCyte 12HT | N37: IZZUDDIN DIWAN | O37: izzuddin.diwan@abcam.com | Q37: 152 GROVE ST STE 1100 | R37: WALTHAM | S37: Massachusetts 02453 | T37: U.S. | U37: =_xlfn.TEXTJOIN(", ", TRUE, Q37, R37, S37, T37) -> 152 GROVE ST STE 1100, WALTHAM, Massachusetts 02453, U.S.
A38: North America | B38: U.S. | C38: EC211336C1 | D38: Abcam Inc | E38: ABCM | F38: US-Boston | H38: Mark Stottlemyer | I38: Lindsay Albert | M38: Guava easyCyte 6HT-2L | N38: IZZUDDIN DIWAN | O38: izzuddin.diwan@abcam.com | Q38: 152 GROVE ST | R38: WALTHAM | S38: Massachusetts 02139 | T38: U.S. | U38: =_xlfn.TEXTJOIN(", ", TRUE, Q38, R38, S38, T38) -> 152 GROVE ST, WALTHAM, Massachusetts 02139, U.S.
A39: North America | B39: U.S. | C39: 8470060215 | D39: Abcam Inc | E39: ABCM | F39: US-Boston | H39: Mark Stottlemyer | I39: Lindsay Albert | M39: Guava easyCyte 6HT-2L | N39: IZZUDDIN DIWAN | O39: izzuddin.diwan@abcam.com | Q39: 152 GROVE ST | R39: WALTHAM | S39: Massachusetts 02139 | T39: U.S. | U39: =_xlfn.TEXTJOIN(", ", TRUE, Q39, R39, S39, T39) -> 152 GROVE ST, WALTHAM, Massachusetts 02139, U.S.
A40: North America | B40: U.S. | C40: 8470060130 | D40: Abcam Inc | E40: ABCM | F40: US-Boston | H40: Mark Stottlemyer | I40: Lindsay Albert | M40: Guava easyCyte 6HT-2L | N40: IZZUDDIN DIWAN | O40: izzuddin.diwan@abcam.com | Q40: 152 GROVE ST STE 1100 | R40: WALTHAM | S40: Massachusetts 02453 | T40: U.S. | U40: =_xlfn.TEXTJOIN(", ", TRUE, Q40, R40, S40, T40) -> 152 GROVE ST STE 1100, WALTHAM, Massachusetts 02453, U.S.
A41: North America | B41: U.S. | C41: 7200150754 | D41: Abcam Inc | E41: ABCM | F41: US-New Haven | H41: Mark Stottlemyer | I41: Lindsay Albert | M41: MUSE CELL ANALYZER SYSTEM | N41: KRISTINA CARLSON | O41: kristina.carlson@abcam.com | Q41: 688 E MAIN ST | R41: BRANFORD | S41: Connecticut 06405 | T41: U.S. | U41: =_xlfn.TEXTJOIN(", ", TRUE, Q41, R41, S41, T41) -> 688 E MAIN ST, BRANFORD, Connecticut 06405, U.S.
A42: North America | B42: U.S. | C42: EC200775A1 | D42: ABS GLOBAL INC | E42: ABS | F42: US-Madison | I42: Robert Thacker | M42: Guava easyCyte 5SL | N42: JENNIFER RINGWELSKI | O42: jringwelski@imvusa.com | Q42: 1525 RIVER RD | R42: DEFOREST | S42: Wisconsin 53532 | T42: U.S. | U42: =_xlfn.TEXTJOIN(", ", TRUE, Q42, R42, S42, T42) -> 1525 RIVER RD, DEFOREST, Wisconsin 53532, U.S.
A43: North America | B43: U.S. | C43: 8472060113 | D43: ABZYME THERAPEUTICS LLC | E43: ABZM | F43: US-Philadelphia | I43: Stephen Weber | M43: Guava easyCyte 6-2L | N43: Sarah Baik | O43: sarah.baik@abzymetx.com | Q43: 321 Jones Blvd. | R43: Pottstown | S43: Pennsylvania 19464 | T43: U.S. | U43: =_xlfn.TEXTJOIN(", ", TRUE, Q43, R43, S43, T43) -> 321 Jones Blvd., Pottstown, Pennsylvania 19464, U.S.
A44: North America | B44: U.S. | C44: 8470050327 | D44: Accent Therapeutics, Inc | E44: ACNT | F44: US-Boston | H44: Mark Stottlemyer | I44: Lindsay Albert | J44: 00031447 | K44: SLA-EC-COMPLETE | L44: Expired | M44: Guava easyCyte 5HT, Boxed Instrument | N44: Bridget Byrne | O44: bbyrne@accenttx.com | Q44: 1050 Waltham St | R44: LEXINGTON | S44: Massachusetts 02421 | T44: U.S. | U44: =_xlfn.TEXTJOIN(", ", TRUE, Q44, R44, S44, T44) -> 1050 Waltham St, LEXINGTON, Massachusetts 02421, U.S.
A45: North America | B45: U.S. | C45: EC232156A2 | D45: Access to Advanced Health Institute (AAHI) | E45: AAHI | H45: Juliane Hill | I45: Leland Brasher | J45: 00031790 | K45: Warranty | L45: Expired | M45: Guava easyCyte 5HT | N45: DARREN KLEMKOW | O45: darren.klemkow@idri.org | Q45: ACCESS TO ADVANCED HEALTH INSTITUTE (AAHI) 1616 Eastlake Ave E SUITE 400 | R45: Seattle | S45: Washington 98102 | T45: U.S. | U45: =_xlfn.TEXTJOIN(", ", TRUE, Q45, R45, S45, T45) -> ACCESS TO ADVANCED HEALTH INSTITUTE (AAHI) 1616 Eastlake Ave E SUITE 400, Seattle, Washington 98102, U.S.
A46: North America | B46: U.S. | C46: 6735125084 | D46: Access to Advanced Health Institute (AAHI) | E46: AAHI | H46: Juliane Hill | I46: Leland Brasher | M46: Guava easyCyte 5HT, Boxed Instrument | Q46: 1616 EASTLAKE AVE E STE 400 | R46: SEATTLE | S46: Washington 98102 | T46: U.S. | U46: =_xlfn.TEXTJOIN(", ", TRUE, Q46, R46, S46, T46) -> 1616 EASTLAKE AVE E STE 400, SEATTLE, Washington 98102, U.S.
A47: North America | B47: U.S. | C47: U0552 | D47: Acerta Pharma LLC | E47: ACRTA | F47: US-Washington DC | G47: Deirdre Johnson-Kimbrough | H47: Sean Cosgriff | I47: Stephen Weber | J47: 00034043 | K47: Premium | L47: Activated | M47: Cytek Aurora 5 Laser UV/V/B/YG/R (64 + 3 Channel) | N47: Raffaello Cimbro | O47: raffaello.cimbro@astrazeneca.com | Q47: One Medimmune Way Room 2638 | R47: Gaithersburg | S47: Maryland 20878 | T47: U.S. | U47: =_xlfn.TEXTJOIN(", ", TRUE, Q47, R47, S47, T47) -> One Medimmune Way Room 2638, Gaithersburg, Maryland 20878, U.S.
A48: North America | B48: U.S. | C48: 6735-R8075 | D48: ACHAOGEN | E48: ACHGN | F48: US-San Francisco | H48: Jonathan Paw | I48: Alexandra Dudschus | M48: Guava EasyCyte 8HT Base System, Refurb | N48: MALAVIKA KANNUSWAMY | O48: mkannuswamy@achaogen.com | Q48: I TOWER PLACE STE 300 | R48: SOUTH SAN FRANCISCO | S48: California 94080 | T48: U.S. | U48: =_xlfn.TEXTJOIN(", ", TRUE, Q48, R48, S48, T48) -> I TOWER PLACE STE 300, SOUTH SAN FRANCISCO, California 94080, U.S.
A49: North America | C49: U1769 | D49: Actus Bio | E49: ACTS | F49: US-Boston | H49: Mark Stottlemyer | I49: Lindsay Albert | J49: 00036138 | K49: Warranty | L49: Activated | M49: Cytek Aurora 5 Laser UV/V/B/YG/R (64 + 3 Channel) | N49: Christine Palmer | O49: cpalmer@actusbio.com | Q49: 1 Kendall Square | R49: Cambridge | S49: Massachusetts 02139 | T49: U.S. | U49: =_xlfn.TEXTJOIN(", ", TRUE, Q49, R49, S49, T49) -> 1 Kendall Square, Cambridge, Massachusetts 02139, U.S.
A50: North America | B50: U.S. | C50: 8470110107 | D50: Adept Therapeutics Inc | E50: ADPT | F50: US-Boston | H50: Mark Stottlemyer | I50: Lindsay Albert | M50: Guava easyCyte 11HT | N50: ERIC HU | O50: changyun.hu@adepttx.com | Q50: 8A HENSHAW ST | R50: WOBURN | S50: Massachusetts 01801 | T50: U.S. | U50: =_xlfn.TEXTJOIN(", ", TRUE, Q50, R50, S50, T50) -> 8A HENSHAW ST, WOBURN, Massachusetts 01801, U.S.
A51: North America | B51: U.S. | C51: 6735145209 | D51: Adept Therapeutics Inc | E51: ADPT | F51: US-Boston | H51: Mark Stottlemyer | I51: Lindsay Albert | M51: Guava easyCyte 5HT, Boxed Instrument | Q51: 8A HENSHAW ST | R51: WOBURN | S51: Massachusetts 01801 | T51: U.S. | U51: =_xlfn.TEXTJOIN(", ", TRUE, Q51, R51, S51, T51) -> 8A HENSHAW ST, WOBURN, Massachusetts 01801, U.S.
A52: North America | B52: U.S. | C52: 8470080160 | D52: Advanced Bioscience Laboratories Inc | E52: ABL | F52: US-Washington DC | H52: Jessica Gucwa | I52: Stephen Weber | J52: 00035240 | K52: SLA-EC-COMPLETE | L52: Activated | M52: Guava easyCyte 8HT | N52: LEON TOUSSAINT | O52: leon.toussaint@ablinc.com | Q52: 9800 MEDICAL CTR DR | R52: ROCKVILLE | S52: Maryland 20850 | T52: U.S. | U52: =_xlfn.TEXTJOIN(", ", TRUE, Q52, R52, S52, T52) -> 9800 MEDICAL CTR DR, ROCKVILLE, Maryland 20850, U.S.
A53: North America | B53: U.S. | C53: 7200121461 | D53: ADVANCED PAIN MEDICINE | E53: APM | F53: US-Pittsburgh | H53: Sean Cosgriff | I53: Karen Young | M53: MUSE CELL ANALYZER SYSTEM | N53: ACACIA FERRESE | O53: acacia@vivatechusa.com | Q53: 1011 BEAVER GRADE RD | R53: MOON | S53: Pennsylvania 15108 | T53: U.S. | U53: =_xlfn.TEXTJOIN(", ", TRUE, Q53, R53, S53, T53) -> 1011 BEAVER GRADE RD, MOON, Pennsylvania 15108, U.S.
A54: North America | B54: U.S. | C54: 8470130126 | D54: AEGLEA BIOSCIENCES | E54: AGLA | F54: US-San Antonio | I54: Eric Barnhart | M54: Guava easyCyte 12HT | N54: Chris Daige | O54: cdaige@aegleabio.com | Q54: 4544 S LAMAR BLVD STE 720 | R54: AUSTIN | S54: Texas 78745 | T54: U.S. | U54: =_xlfn.TEXTJOIN(", ", TRUE, Q54, R54, S54, T54) -> 4544 S LAMAR BLVD STE 720, AUSTIN, Texas 78745, U.S.
A55: North America | B55: U.S. | C55: Y0020 | D55: Aera Therapeutics Inc | E55: AERA | F55: US-Boston | H55: Mark Stottlemyer | I55: Lindsay Albert | J55: 00036111 | K55: Warranty | L55: Activated | M55: Cytek Aurora 5 Laser UV/V/B/YG/R (64 + 3 Channel) - REFURBISHED | N55: Samuel Mohler | O55: samuel.mohler@aeratx.com | Q55: 300 Technology Square 6th Floor | R55: Cambridge | S55: Massachusetts 02139 | T55: U.S. | U55: =_xlfn.TEXTJOIN(", ", TRUE, Q55, R55, S55, T55) -> 300 Technology Square 6th Floor, Cambridge, Massachusetts 02139, U.S.
A56: North America | B56: U.S. | C56: FS167 | D56: AFERNA BIO | E56: AFRNA | F56: US-St. Louis | I56: Robert Thacker | M56: Amnis FlowSight System, Obsolete | N56: MATTHEW CROXFORD | O56: matt.croxford@afernabio.com | Q56: 1100 CORPORATE SQUARE DR STE 175 | R56: SAINT LOUIS | S56: Missouri 63132 | T56: U.S. | U56: =_xlfn.TEXTJOIN(", ", TRUE, Q56, R56, S56, T56) -> 1100 CORPORATE SQUARE DR STE 175, SAINT LOUIS, Missouri 63132, U.S.
A57: North America | B57: U.S. | C57: 8470050274 | D57: AGC Biologics | E57: AGC | H57: Juliane Hill | I57: Leland Brasher | M57: Guava easyCyte 5HT, Boxed Instrument | Q57: 22032 23RD DR SE | R57: BOTHELL | S57: Washington 98021 | T57: U.S. | U57: =_xlfn.TEXTJOIN(", ", TRUE, Q57, R57, S57, T57) -> 22032 23RD DR SE, BOTHELL, Washington 98021, U.S.
A58: North America | C58: 8470-R5131 | D58: AGC Biologics | E58: ACG | H58: Juliane Hill | I58: Leland Brasher | N58: TSERING SANGMO | O58: tsangmo@agcbio.com | U58: =_xlfn.TEXTJOIN(", ", TRUE, Q58, R58, S58, T58)
A59: North America | B59: U.S. | C59: 7200121505 | D59: AGENUS INC | E59: AGNS | H59: Mark Stottlemyer | I59: Lindsay Albert | M59: MUSE CELL ANALYZER SYSTEM | Q59: 3 FORBES ROAD | R59: LEXINGTON | S59: Massachusetts 02421-7305 | T59: U.S. | U59: =_xlfn.TEXTJOIN(", ", TRUE, Q59, R59, S59, T59) -> 3 FORBES ROAD, LEXINGTON, Massachusetts 02421-7305, U.S.
A60: North America | B60: U.S. | C60: 7200121344 | D60: AGENUS INC | E60: AGNS | H60: Mark Stottlemyer | I60: Lindsay Albert | M60: MUSE CELL ANALYZER SYSTEM | Q60: 3 FORBES ROAD | R60: LEXINGTON | S60: Massachusetts 02421-7305 | T60: U.S. | U60: =_xlfn.TEXTJOIN(", ", TRUE, Q60, R60, S60, T60) -> 3 FORBES ROAD, LEXINGTON, Massachusetts 02421-7305, U.S.
A61: North America | B61: U.S. | C61: 7200121000 | D61: AGENUS INC | E61: AGNS | H61: Mark Stottlemyer | I61: Lindsay Albert | M61: MUSE CELL ANALYZER SYSTEM | Q61: 3 FORBES ROAD | R61: LEXINGTON | S61: Massachusetts 02421-7305 | T61: U.S. | U61: =_xlfn.TEXTJOIN(", ", TRUE, Q61, R61, S61, T61) -> 3 FORBES ROAD, LEXINGTON, Massachusetts 02421-7305, U.S.
A62: North America | B62: U.S. | C62: 8470060152 | D62: Agios Pharmaceuticals Inc | E62: AGIOS | F62: US-Boston | H62: Mark Stottlemyer | I62: Lindsay Albert | M62: Guava easyCyte 6HT-2L | N62: COURTNEY GOODMAN | O62: courtney.goodman@agios.com | Q62: 88 SIDNEY ST 1ST FL | R62: CAMBRIDGE | S62: Massachusetts 02139 | T62: U.S. | U62: =_xlfn.TEXTJOIN(", ", TRUE, Q62, R62, S62, T62) -> 88 SIDNEY ST 1ST FL, CAMBRIDGE, Massachusetts 02139, U.S.
A63: North America | B63: U.S. | C63: 6735138207 | D63: AKSTON BIOSCIENCES CORPORATION | E63: AKSTN | F63: US-Boston | I63: Lindsay Albert | M63: Guava easyCyte 8HT | Q63: 100 CUMMINGS CTR STE 336H | R63: BEVERLY | S63: Massachusetts 01915 | T63: U.S. | U63: =_xlfn.TEXTJOIN(", ", TRUE, Q63, R63, S63, T63) -> 100 CUMMINGS CTR STE 336H, BEVERLY, Massachusetts 01915, U.S.
A64: North America | B64: U.S. | C64: 6620125090 | D64: ALBANY COLLEGE OF PHARMACY | E64: ACOP | F64: US-Boston | H64: Mark Stottlemyer | I64: Lindsay Albert | M64: Guava easyCyte 5SL | Q64: 261 MOUTAIN VIEW DR | R64: COLCHESTER | S64: Vermont 05446 | T64: U.S. | U64: =_xlfn.TEXTJOIN(", ", TRUE, Q64, R64, S64, T64) -> 261 MOUTAIN VIEW DR, COLCHESTER, Vermont 05446, U.S.
A65: North America | B65: U.S. | C65: 7200150916 | D65: Albany College of Pharmacy and Health Sciences (ACPHS) | E65: ACPHS | F65: US-Albany | I65: Siu-hong Ho | M65: MUSE CELL ANALYZER SYSTEM | N65: MARIE MALONE | O65: kmalone7515@gmail.com | Q65: 9 SAMARITAN RD | R65: ALBANY | S65: New York 12208 | T65: U.S. | U65: =_xlfn.TEXTJOIN(", ", TRUE, Q65, R65, S65, T65) -> 9 SAMARITAN RD, ALBANY, New York 12208, U.S.
A66: North America | B66: U.S. | C66: ISX346 | D66: Albany Medical Center | E66: AMC | F66: US-Albany | G66: John Grady | H66: Jason Emo | I66: Siu-hong Ho | J66: 00033026 | K66: SLA-ISXMKII-BASIC | L66: Activated | M66: Amnis ImageStreamX MkII System w/ INSPIRE & IDEAS Software | N66: Bill O'Connor | O66: oconnow@amc.edu | Q66: 43 NEW SCOTLAND AVE RM MS242 | R66: ALBANY | S66: New York 12208 | T66: U.S. | U66: =_xlfn.TEXTJOIN(", ", TRUE, Q66, R66, S66, T66) -> 43 NEW SCOTLAND AVE RM MS242, ALBANY, New York 12208, U.S.
A67: North America | B67: U.S. | C67: 7200150628 | D67: Albany Medical Center | E67: AMC | F67: US-Albany | G67: John Grady | H67: Jason Emo | I67: Siu-hong Ho | M67: MUSE CELL ANALYZER SYSTEM | N67: STEVE HIGGINS | O67: higgins@amc.edu | Q67: 1275 BROADWAY | R67: MENANDS | S67: New York 12204 | T67: U.S. | U67: =_xlfn.TEXTJOIN(", ", TRUE, Q67, R67, S67, T67) -> 1275 BROADWAY, MENANDS, New York 12204, U.S.
A68: North America | B68: U.S. | C68: NM1255 | D68: Albany Medical College | E68: AMC | G68: Josiah Minotto | H68: Amay Dankar | I68: Siu-hong Ho | J68: 00030823 | K68: Value | L68: Activated | M68: Cytek Northern Lights 3000 V/B/R - (38 + 3 channel) | N68: Kate MacNamara | O68: macnamk@amc.edu | Q68: AMC Receiving Dock 43 New Scotland Avenue Room FB-14 | R68: Albany | S68: New York 12208-3478 | T68: U.S. | U68: =_xlfn.TEXTJOIN(", ", TRUE, Q68, R68, S68, T68) -> AMC Receiving Dock 43 New Scotland Avenue Room FB-14, Albany, New York 12208-3478, U.S.
A69: North America | B69: U.S. | C69: 8472080101 | D69: Albany Medical College | E69: AMC | F69: US-Albany | G69: Josiah Minotto | H69: Amay Dankar | I69: Siu-hong Ho | M69: Guava easyCyte 8 | N69: FRAN JOURDHEUIL | O69: jourdhf@mail.amc.edu | Q69: 43 NEW SCOTLAND AVE - MAIN | R69: ALBANY | S69: New York 12208 | T69: U.S. | U69: =_xlfn.TEXTJOIN(", ", TRUE, Q69, R69, S69, T69) -> 43 NEW SCOTLAND AVE - MAIN, ALBANY, New York 12208, U.S.
A70: North America | B70: U.S. | C70: 8470060140 | D70: Albany Medical College | E70: AMC | F70: US-Albany | G70: Josiah Minotto | H70: Amay Dankar | I70: Siu-hong Ho | M70: Guava easyCyte 6HT-2L | N70: AMIT SINGH | O70: singha5@amc.edu | Q70: 43 NEW SCOTLAND AVE | R70: ALBANY | S70: New York 12208 | T70: U.S. | U70: =_xlfn.TEXTJOIN(", ", TRUE, Q70, R70, S70, T70) -> 43 NEW SCOTLAND AVE, ALBANY, New York 12208, U.S.
A71: North America | B71: U.S. | C71: U1408SP | D71: Albert Einstein College of Medicine | E71: AECOM | F71: US-New York City | G71: Josiah Minotto | H71: Jason Emo | I71: Siu-hong Ho | J71: 00033361 | K71: Premium | L71: Activated | M71: Cytek Aurora 5 Laser UV/V/B/YG/R (64 + 3 Channel) | N71: Yu Zhang | O71: yu.zhang@einstein.yu.edu | Q71: Bldg/Rm: Price Center, Room 159 B 1300 Morris Park Avenue | R71: Bronx | S71: New York 10461 | T71: U.S. | U71: =_xlfn.TEXTJOIN(", ", TRUE, Q71, R71, S71, T71) -> Bldg/Rm: Price Center, Room 159 B 1300 Morris Park Avenue, Bronx, New York 10461, U.S.
A72: North America | B72: U.S. | C72: U0304 | D72: Albert Einstein College of Medicine | E72: AECOM | F72: US-New York City | G72: Josiah Minotto | H72: Jason Emo | I72: Siu-hong Ho | J72: 00013881 | K72: Premium | L72: Activated | M72: Cytek Aurora 5 Laser UV/V/B/YG/R (64 + 3 Channel) | N72: Fnu Aodengtuya | O72: fnu.aodengtuya@einsteinmed.edu | Q72: Rm 309, Chanin Bldg 1300 Morris Park Ave | R72: Bronx | S72: New York 10461 | T72: U.S. | U72: =_xlfn.TEXTJOIN(", ", TRUE, Q72, R72, S72, T72) -> Rm 309, Chanin Bldg 1300 Morris Park Ave, Bronx, New York 10461, U.S.
A73: North America | B73: U.S. | C73: U0263 | D73: Albert Einstein College of Medicine | E73: AECOM | F73: US-New York City | G73: Josiah Minotto | H73: Jason Emo | I73: Siu-hong Ho | J73: 00033618 | K73: Premium | L73: Activated | M73: Cytek Aurora 5 Laser UV/V/B/YG/R (64 + 3 Channel) | N73: Jinghang Zhang | O73: jinghang.zhang@einsteinmed.edu | Q73: Rm 309, Chanin Bldg 1300 Morris Park Ave | R73: Bronx | S73: New York 10461 | T73: U.S. | U73: =_xlfn.TEXTJOIN(", ", TRUE, Q73, R73, S73, T73) -> Rm 309, Chanin Bldg 1300 Morris Park Ave, Bronx, New York 10461, U.S.
A74: North America | B74: U.S. | C74: S0335 | D74: Albert Einstein College of Medicine | E74: AECOM | F74: US-New York City | G74: Josiah Minotto | H74: Jason Emo | I74: Siu-hong Ho | J74: 00034130 | K74: Warranty | L74: Activated | M74: Cytek Aurora-CS 5L System | N74: Jinghang Zhang | O74: jinghang.zhang@einsteinmed.edu | Q74: 1300 Morris Park Avenue | R74: Bronx | S74: New York 10461 | T74: U.S. | U74: =_xlfn.TEXTJOIN(", ", TRUE, Q74, R74, S74, T74) -> 1300 Morris Park Avenue, Bronx, New York 10461, U.S.
A75: North America | B75: U.S. | C75: S0276 | D75: Albert Einstein College of Medicine | E75: AECOM | F75: US-New York City | G75: Josiah Minotto | H75: Jason Emo | I75: Siu-hong Ho | J75: 00031432 | K75: Premium | L75: Activated | M75: Cytek Aurora-CS 5L System | N75: Daqian Sun | O75: daqian.sun@einsteinmed.edu | Q75: Albert Einstein College of Medicine 1300 Morris Park Ave, Chanin Bldg, Rm 638A phone x3551 | R75: Bronx | S75: New York 10461 | T75: U.S. | U75: =_xlfn.TEXTJOIN(", ", TRUE, Q75, R75, S75, T75) -> Albert Einstein College of Medicine 1300 Morris Park Ave, Chanin Bldg, Rm 638A phone x3551, Bronx, New York 10461, U.S.
A76: North America | C76: S0373SP | D76: Albert Einstein College of Medicine | E76: AECOM | F76: US-New York City | G76: Josiah Minotto | H76: Jason Emo | I76: Siu-hong Ho | J76: 00034946 | K76: Warranty | L76: Activated | M76: Cytek Aurora-CS 5L System | N76: Jinghang Zhang | O76: jinghang.zhang@einsteinmed.edu | Q76: 1300 Morris Park Avenue | R76: Bronx | S76: New York 10461 | T76: U.S. | U76: =_xlfn.TEXTJOIN(", ", TRUE, Q76, R76, S76, T76) -> 1300 Morris Park Avenue, Bronx, New York 10461, U.S.
A77: North America | B77: U.S. | C77: U1574 | D77: Alexion Pharmaceuticals Inc | E77: ALXN | F77: US-New Haven | G77: Moid Ather | H77: Jason Emo | I77: Siu-hong Ho | J77: 00036150 | K77: Premium | L77: Activated | M77: Cytek Aurora 5 Laser UV/V/B/YG/R (64 + 3 Channel) | N77: Mike Feulner | O77: mike.feulner@alexion.com | Q77: 101 College Street | R77: New Haven | S77: Connecticut 06510 | T77: U.S. | U77: =_xlfn.TEXTJOIN(", ", TRUE, Q77, R77, S77, T77) -> 101 College Street, New Haven, Connecticut 06510, U.S.
A78: North America | B78: U.S. | C78: NM1239 | D78: Alexion Pharmaceuticals Inc | E78: ALXN | F78: US-New Haven | G78: Moid Ather | H78: Jason Emo | I78: Siu-hong Ho | J78: 00034574 | K78: Premium | L78: Activated | M78: Cytek Northern Lights 3000 V/B/R - (38 + 3 channel) | N78: Yongsen Zhao | O78: yongsen.zhao@alexion.com | Q78: 3rd floor, #301 300 George Street | R78: New Haven | S78: Connecticut 06511 | T78: U.S. | U78: =_xlfn.TEXTJOIN(", ", TRUE, Q78, R78, S78, T78) -> 3rd floor, #301 300 George Street, New Haven, Connecticut 06511, U.S.
A79: North America | B79: U.S. | C79: FS331 | D79: Alexion Pharmaceuticals Inc | E79: ALXN | F79: US-New Haven | G79: Moid Ather | H79: Jason Emo | I79: Siu-hong Ho | J79: 00032310 | K79: SLA-FS-COMPLETE | L79: Expired | M79: FlowSight Instrument | N79: PETE PELCZAR | O79: pete.pelczar@alexion.com | Q79: 100 COLLEGE ST | R79: NEW HAVEN | S79: Connecticut 06510 | T79: U.S. | U79: =_xlfn.TEXTJOIN(", ", TRUE, Q79, R79, S79, T79) -> 100 COLLEGE ST, NEW HAVEN, Connecticut 06510, U.S.
A80: North America | B80: U.S. | C80: EC231396C1 | D80: Alexion Pharmaceuticals Inc | E80: ALXN | F80: US-New Haven | G80: Moid Ather | H80: Jason Emo | I80: Siu-hong Ho | J80: 00034109 | K80: SLA-EC-COMPLETE | L80: Activated | M80: Guava easyCyte 6HT-2L | N80: XINLEI CHEN | O80: xinlei.chen@alexion.com | Q80: 100 COLLEGE STREET AL17 PO#4800071900 | R80: New Haven | S80: Connecticut 06510 | T80: U.S. | U80: =_xlfn.TEXTJOIN(", ", TRUE, Q80, R80, S80, T80) -> 100 COLLEGE STREET AL17 PO#4800071900, New Haven, Connecticut 06510, U.S.
A81: North America | B81: U.S. | C81: 8470060257 | D81: Alexion Pharmaceuticals Inc | E81: ALXN | F81: US-Raleigh-Durham | G81: Moid Ather | H81: Jason Emo | I81: Siu-hong Ho | J81: 00024114 | K81: SLA-EC-COMPLETE | L81: Expired | M81: Guava easyCyte 6HT-2L | Q81: 7030 KIT CREEK RD RM 2007 | R81: MORRISVILLE | S81: North Carolina 27560 | T81: U.S. | U81: =_xlfn.TEXTJOIN(", ", TRUE, Q81, R81, S81, T81) -> 7030 KIT CREEK RD RM 2007, MORRISVILLE, North Carolina 27560, U.S.
A82: North America | C82: U1776 | D82: Alexion Pharmaceuticals Inc | E82: ALXN | F82: US-New Haven | G82: Moid Ather | H82: Jason Emo | I82: Siu-hong Ho | J82: 00036246 | K82: Warranty | L82: Activated | M82: Cytek Aurora 5 Laser UV/V/B/YG/R (64 + 3 Channel) | N82: Mike Feulner | O82: mike.feulner@alexion.com | Q82: 101 College Street, Floor 7 | R82: New Haven | S82: Connecticut 06511 | T82: U.S. | U82: =_xlfn.TEXTJOIN(", ", TRUE, Q82, R82, S82, T82) -> 101 College Street, Floor 7, New Haven, Connecticut 06511, U.S.
A83: North America | B83: U.S. | C83: NM1078 | D83: Alexion Pharmaceuticals Inc - Cambridge MA | E83: ALXN | F83: US-Boston | G83: James Martin | H83: Mark Stottlemyer | I83: Lindsay Albert | J83: 00033700 | K83: Premium | L83: Expired | M83: Cytek Northern Lights 3000 V/B/R - (38 + 3 channel) | N83: Mark Johnson | O83: mark.johnson1@alexion.com | Q83: 100 Binney Street - Room IHC 376 | R83: Cambridge | S83: Massachusetts 02139 | T83: U.S. | U83: =_xlfn.TEXTJOIN(", ", TRUE, Q83, R83, S83, T83) -> 100 Binney Street - Room IHC 376, Cambridge, Massachusetts 02139, U.S.
A84: North America | B84: U.S. | C84: 6735128163 | D84: ALL AMERICAN SELF STORAGE | E84: AASS | F84: US-Minneapolis | I84: Integration User | M84: Guava easyCyte 8HT, Boxed Instrument | Q84: 670 PELHAM BLVD UNIT 233 | R84: ST PAUL | S84: Minnesota 55114 | T84: U.S. | U84: =_xlfn.TEXTJOIN(", ", TRUE, Q84, R84, S84, T84) -> 670 PELHAM BLVD UNIT 233, ST PAUL, Minnesota 55114, U.S.
A85: North America | B85: U.S. | C85: ISX508 | D85: Allegheny College | E85: ALGNY | F85: US-Pittsburgh | H85: Sean Cosgriff | I85: Karen Young | J85: 00034041 | K85: SLA-ISXMKII-BASIC | L85: Activated | M85: ImageStreamX MkII Instrument | N85: TRICIA HUMPHREYS | O85: thumphre@allegheny.edu | Q85: 433 PARK AVE | R85: MEADVILLE | S85: Pennsylvania 16335 | T85: U.S. | U85: =_xlfn.TEXTJOIN(", ", TRUE, Q85, R85, S85, T85) -> 433 PARK AVE, MEADVILLE, Pennsylvania 16335, U.S.
A86: North America | B86: U.S. | C86: S0329 | D86: Allergan Aesthetics - an Abbvie company | E86: ALRGN | F86: US-Burbank | G86: Mahmoud Ajine | H86: Aric Bitton | I86: Sarah Christy | J86: 00036630 | K86: Premium | L86: Activated | M86: Cytek Aurora-CS 3L system | N86: Adriana Marin | O86: adriana.marin@abbvie.com | Q86: 18655 Teller Ave RD3-2D | R86: Irvine | S86: California 92612 | T86: U.S. | U86: =_xlfn.TEXTJOIN(", ", TRUE, Q86, R86, S86, T86) -> 18655 Teller Ave RD3-2D, Irvine, California 92612, U.S.
A87: North America | B87: U.S. | C87: NM1212 | D87: Allergan Aesthetics - an Abbvie company | E87: ALRGN | F87: US-Burbank | G87: Mahmoud Ajine | H87: Aric Bitton | I87: Sarah Christy | J87: 00032833 | K87: Premium | L87: Activated | M87: Cytek Northern Lights 3000 V/B/R - (38 + 3 channel) | N87: Laura McIntyre | O87: equipmentconciergeservice@abbvie.com | Q87: 18655 Teller Ave | R87: IRVINE | S87: California 92612 | T87: U.S. | U87: =_xlfn.TEXTJOIN(", ", TRUE, Q87, R87, S87, T87) -> 18655 Teller Ave, IRVINE, California 92612, U.S.
A88: North America | B88: U.S. | C88: 6735135186 | D88: Allergan Aesthetics - an Abbvie company | E88: ALRGN | F88: US-Burbank | G88: Mahmoud Ajine | H88: Aric Bitton | I88: Sarah Christy | M88: Guava easyCyte 5HT, Boxed Instrument | Q88: 18600 VON KARMAN AVE | R88: IRVINE | S88: California 92612 | T88: U.S. | U88: =_xlfn.TEXTJOIN(", ", TRUE, Q88, R88, S88, T88) -> 18600 VON KARMAN AVE, IRVINE, California 92612, U.S.
A89: North America | C89: 6620135129 | D89: Allergan Aesthetics - an Abbvie company | E89: ALRGN | G89: Mahmoud Ajine | H89: Aric Bitton | I89: Sarah Christy | M89: Guava easyCyte 5SL | T89: U.S. | U89: =_xlfn.TEXTJOIN(", ", TRUE, Q89, R89, S89, T89) -> , U.S.
A90: North America | B90: U.S. | C90: NM1596 | D90: Alliance Funding Group | E90: AFG | F90: US-Houston | G90: Jesse Martinez | H90: Loni Perrenoud | I90: Eric Barnhart | J90: 00034131 | K90: Warranty | L90: Activated | M90: Cytek Northern Lights 1000 B - 14 channel | N90: Steve Friedrich | O90: sfriedrich@afg.com | Q90: 2402 Marina Bay Dr | R90: League | S90: Texas 77573 | T90: U.S. | U90: =_xlfn.TEXTJOIN(", ", TRUE, Q90, R90, S90, T90) -> 2402 Marina Bay Dr, League, Texas 77573, U.S.
A91: North America | B91: U.S. | C91: U1215 | D91: Allogene Therapeutics | E91: ALGNE | F91: US-San Francisco | G91: Aldrin Aragon | H91: Jonathan Paw | I91: Leland Brasher | J91: 00034415 | K91: Value | L91: Activated | M91: Cytek Aurora 5 Laser UV/V/B/YG/R (64 + 3 Channel) | N91: Craig Hobizal | O91: craig.hobizal@allogene.com | Q91: 210 East Grand Ave | R91: South San Francisco | S91: California 94080 | T91: U.S. | U91: =_xlfn.TEXTJOIN(", ", TRUE, Q91, R91, S91, T91) -> 210 East Grand Ave, South San Francisco, California 94080, U.S.
A92: North America | B92: U.S. | C92: RM1001 | D92: Alloy Therapeutics | E92: ALLY | F92: US-Boston | G92: James Martin | H92: Mark Stottlemyer | I92: Lindsay Albert | J92: 00033539 | K92: Premium | L92: Expired | M92: Cytek Aurora 3 Laser V/B/R - (38 + 3 Channel) | N92: TYLER FALING | O92: tyler.faling@alloytx.com | Q92: 275 2nd Ave. Ste 200 | R92: Waltham | S92: Massachusetts 02451 | T92: U.S. | U92: =_xlfn.TEXTJOIN(", ", TRUE, Q92, R92, S92, T92) -> 275 2nd Ave. Ste 200, Waltham, Massachusetts 02451, U.S.
A93: North America | C93: FS314 | D93: Alpha Nano Tech LLC | E93: ALPHA | H93: Sean Cosgriff | I93: Rob Dell'Orco | M93: FlowSight Instrument | N93: Nazar Filonov | O93: nazar@alphanano.tech | T93: U.S. | U93: =_xlfn.TEXTJOIN(", ", TRUE, Q93, R93, S93, T93) -> , U.S.
A94: North America | B94: U.S. | C94: 8470050205 | D94: ALS Therapy Development Institute (ALS TDI) | E94: ALSTDI | F94: US-Boston | G94: Kwynn Guess | H94: Mark Stottlemyer | I94: Lindsay Albert | J94: 00034362 | K94: SLA-EC-COMPLETE | L94: Activated | M94: Guava easyCyte 5HT, Boxed Instrument | N94: CINDY GILL | O94: cgill@als.net | Q94: 480 Arsenal Way, Suite 201 | R94: Watertown | S94: Massachusetts 02472 | T94: U.S. | U94: =_xlfn.TEXTJOIN(", ", TRUE, Q94, R94, S94, T94) -> 480 Arsenal Way, Suite 201, Watertown, Massachusetts 02472, U.S.
A95: North America | B95: CA | C95: EC211096A1 | D95: Alta Genetics Inc | E95: ALTA | F95: CA-Calgary | H95: Juliane Hill | I95: Gregory Kleedtke | J95: 00030360 | K95: SLA-EC-COMPLETE | L95: Activated | M95: Guava easyCyte 5HT, Boxed Instrument | N95: Thomas Jacob | O95: thomas.jacob@urus.org | Q95: 1-263090 RANGE RD 11 | R95: ROCKY VIEW COUNTY | S95: Alberta T4B 2T3 | T95: CA | U95: =_xlfn.TEXTJOIN(", ", TRUE, Q95, R95, S95, T95) -> 1-263090 RANGE RD 11, ROCKY VIEW COUNTY, Alberta T4B 2T3, CA
A96: North America | B96: U.S. | C96: 6735-R8176 | D96: AMBRX INC | E96: AMBRIX | F96: US-San Diego | I96: Sarah Christy | M96: Guava EasyCyte 8HT Base System, Refurb | N96: PETRA PHAM | O96: petra.pham@ambrx.com | Q96: 10975 N TORREY PINES RD | R96: LA JOLLA | S96: California 92037 | T96: U.S. | U96: =_xlfn.TEXTJOIN(", ", TRUE, Q96, R96, S96, T96) -> 10975 N TORREY PINES RD, LA JOLLA, California 92037, U.S.
A97: North America | B97: U.S. | C97: 8470080208 | D97: AMENTUM SERVICES INC | E97: AMNTM | F97: US-Jacksonville | H97: Sean Cosgriff | I97: Karen Young | J97: 00033978 | K97: SLA-EC-INTERMED | L97: Expired | M97: Guava easyCyte 8HT | N97: Jeff Richards | O97: jeffrey.t.richards@nasa.gov | Q97: LASSO / LABS BLDG M6-0744 | R97: KENNEDY SPACE CENTER | S97: Florida 32899 | T97: U.S. | U97: =_xlfn.TEXTJOIN(", ", TRUE, Q97, R97, S97, T97) -> LASSO / LABS BLDG M6-0744, KENNEDY SPACE CENTER, Florida 32899, U.S.
A98: North America | B98: U.S. | C98: 8470060218 | D98: AMESINO LLC | E98: AMNS | F98: US-Memphis | I98: Katherine Fonte | M98: Guava easyCyte 6HT-2L | N98: XIAOYUN WU | O98: xiaoyunwu656@yahoo.com | Q98: 1500 1ST AVE N STE L109 UNIT 33 | R98: BIRMINGHAM | S98: Alabama 35203 | T98: U.S. | U98: =_xlfn.TEXTJOIN(", ", TRUE, Q98, R98, S98, T98) -> 1500 1ST AVE N STE L109 UNIT 33, BIRMINGHAM, Alabama 35203, U.S.
A99: North America | B99: CA | C99: U1587 | D99: Amgen British Columbia | E99: AMGEN | F99: CA-Vancouver | G99: Ivan Nosov | H99: Juliane Hill | I99: Karen Young | J99: 00035142 | K99: Premium | L99: Activated | M99: Cytek Aurora 5 Laser UV/V/B/YG/R (64 + 3 Channel) | N99: Mario Fidanza | O99: mfidanza@amgen.com | Q99: 7990 Enterprise St. | R99: Burnaby | S99: British Columbia V5A 1V7 | T99: CA | U99: =_xlfn.TEXTJOIN(", ", TRUE, Q99, R99, S99, T99) -> 7990 Enterprise St., Burnaby, British Columbia V5A 1V7, CA
A100: North America | B100: CA | C100: 8470130169 | D100: Amgen British Columbia | E100: AMGN | F100: CA-Vancouver | G100: Ivan Nosov | H100: Juliane Hill | I100: Karen Young | J100: 00034456 | K100: SLA-EC-COMPLETE | L100: Activated | M100: Guava easyCyte 12HT | N100: Hope Rezk | O100: hibarra@amgen.com | Q100: 7990 Entreprise Rd | R100: Burnaby | S100: British Columbia V5A 1V7 | T100: CA | U100: =_xlfn.TEXTJOIN(", ", TRUE, Q100, R100, S100, T100) -> 7990 Entreprise Rd, Burnaby, British Columbia V5A 1V7, CA
...

Sheet Pricing Data
A1: Display Name | B1: Last Purchase Price | C1: Sale Unit | D1: Unit Price | E1: Price Level | F1: Currency | G1: Part Number | H1: Item Internal ID
A2: Value contract deductible | D2: 750 | F2: US Dollar | G2: Value
A3: On-Site Support (2 days) | D3: 7571 | F3: US Dollar | G3: 60020
A4: Basic contract deductible | F4: US Dollar
A5: Vacuum Manifold | B5: 58.56 | C5: Each | D5: 274.64 | E5: List Price | F5: US Dollar | G5: N0-00001 | H5: 34749
A6: Mounting Plate | B6: 2.12 | C6: Each | D6: 7.76 | E6: List Price | F6: US Dollar | G6: N0-00002 | H6: 16742
A7: Valve Guide | B7: 7.46 | C7: Each | D7: 22.38 | E7: List Price | F7: US Dollar | G7: N0-00003 | H7: 16743
A8: Pinch Hammer | B8: 0 | C8: Each | D8: 33.57 | E8: List Price | F8: US Dollar | G8: N0-00004 | H8: 16744
A9: Pinch Head | B9: 0 | C9: Each | D9: 80.61 | E9: List Price | F9: US Dollar | G9: N0-00005 | H9: 16745
A10: DeGasser Bracket | B10: 3.34 | C10: Each | D10: 12.53 | E10: List Price | F10: US Dollar | G10: N0-00006 | H10: 16746
A11: Lens Retaining Cover | B11: 3.6 | C11: Each | D11: 37.38 | E11: List Price | F11: US Dollar | G11: N0-00009 | H11: 16747
A12: Lens Barrel | B12: 21.81 | C12: Each | D12: 141.56 | E12: List Price | F12: US Dollar | G12: N0-00010 | H12: 16748
A13: Flow Cell Body | B13: 114.06 | C13: Each | D13: 268.71 | E13: List Price | F13: US Dollar | G13: N0-00011 | H13: 16752
A14: Flow Cell Exit | B14: 20.57 | C14: Each | D14: 53.73 | E14: List Price | F14: US Dollar | G14: N0-00012 | H14: 16753
A15: SIT Base | B15: 12.69 | C15: Each | D15: 38.07 | E15: List Price | F15: US Dollar | G15: N0-00013 | H15: 16754
A16: Red Prism Block | B16: 11.49 | C16: Each | D16: 57.09 | E16: List Price | F16: US Dollar | G16: N0-00014 | H16: 16757
... A1085: 0.07" EPDM O-ring Cord Stock | B1085: 0.27 | C1085: Foot | D1085: 0.02461 | E1085: List Price | F1085: US Dollar | G1085: N4-00095 | H1085: 75631
A1087: MMC 9616K11
A1088: O-RING, AS568A-159, EPDM 70 DURO | B1088: 12.16 | C1088: Each | D1088: 0.48 | E1088: List Price | F1088: US Dollar | G1088: N4-00100 | H1088: 15287
A1089: 1/4-28 x 1/8 FEMALE Luer BARB PANEL MT | B1089: 0.57 | C1089: Each | D1089: 1.52 | E1089: List Price | F1089: US Dollar | G1089: N4-00104 | H1089: 15319
A1090: Tee Tube Fitting with Classic Series Barbs, 1/8" (3.2 | B1090: 1.04 | C1090: Each | D1090: 2.67 | E1090: List Price | F1090: US Dollar | G1090: N4-00105 | H1090: 15339
A1091: Aria 1/32" Ferrule for PEEK Tubing in PMI Kit | B1091: 2 | C1091: Each | D1091: 9.21 | E1091: List Price | F1091: US Dollar | G1091: N4-00106 | H1091: 15342
A1092: ALMOND BULKHEAD 1/8" | B1092: 7.91 | C1092: Each | D1092: 41.91 | E1092: List Price | F1092: US Dollar | G1092: N4-00107 | H1092: 15370
A1093: FEMALE 1/4 NPT COLDER | B1093: 6.47 | C1093: Each | D1093: 29.43 | E1093: List Price | F1093: US Dollar | G1093: N4-00112 | H1093: 15373
A1094: ALMOND MALE COLDER 1/8" | B1094: 5.51 | C1094: Each | D1094: 18.33 | E1094: List Price | F1094: US Dollar | G1094: N4-00114 | H1094: 15376
A1095: ORG MALE COLDER 1/8" | B1095: 7.05 | C1095: Each | D1095: 18.33 | E1095: List Price | F1095: US Dollar | G1095: N4-00116 | H1095: 49212
A1096: SHEATH LEVEL SENSOR CAP | B1096: 3.56 | C1096: Each | D1096: 46.68 | E1096: List Price | F1096: US Dollar | G1096: N4-00118 | H1096: 15485
A1097: NC FLOAT SWITCH Brown Wires | B1097: 35.74 | C1097: Each | D1097: 94.74 | E1097: List Price | F1097: US Dollar | G1097: N4-00120 | H1097: 15490
A1098: Pressure Transducer Athena/Rainbow | B1098: 48.99 | C1098: Each | D1098: 183 | E1098: List Price | F1098: US Dollar | G1098: N4-00122 | H1098: 15567
A1099: 4L Tank | B1099: 126.9 | C1099: Each | D1099: 137.22 | E1099: List Price | F1099: US Dollar | G1099: N4-00124 | H1099: 15568
... A2662: RYV Upgrade (Monthly) | B2662: 0 | C2662: Each | D2662: 525 | E2662: List Price | F2662: US Dollar | G2662: N9-90097 | H2662: 105652
A2663: OQ Package (2PM visits) | B2663: 0 | D2663: 10500 | E2663: List Price | F2663: US Dollar | G2663: N9-90099 | H2663: 68075
A2664: OQ Package (All service visits) | B2664: 0 | D2664: 15750 | E2664: List Price | F2664: US Dollar | G2664: N9-90100 | H2664: 68076
A2665: IQ/OQ | B2665: 0 | D2665: 10500 | E2665: List Price | F2665: US Dollar | G2665: N9-90101 | H2665: 22353
A2666: Annual Surcharge | B2666: 0 | C2666: Each | D2666: 1313 | E2666: List Price | F2666: US Dollar | G2666: N9-90102 | H2666: 65838
A2667: Quarterly Surcharge | B2667: 0 | C2667: Each | D2667: 2625 | E2667: List Price | F2667: US Dollar | G2667: N9-90103 | H2667: 65839
A2668: BSL3/4 Surcharge | B2668: 0 | C2668: Each | D2668: 10500 | E2668: List Price | F2668: US Dollar | G2668: N9-90104 | H2668: 109579
A2669: BSL3/4 Surcharge | B2669: 0 | C2669: Each | D2669: 10000 | E2669: List Price | F2669: US Dollar | G2669: N9-90104-INA | H2669: 65840
A2670: Priority Response | B2670: 0 | C2670: Each | D2670: 1575 | E2670: List Price | F2670: US Dollar | G2670: N9-90105 | H2670: 20180
A2671: Cytek Spectral Cytometry Additional Training Provisions | B2671: 0 | C2671: Each | D2671: 5516 | E2671: List Price | F2671: US Dollar | G2671: N9-90106 | H2671: 68301
A2672: Cytek Spectral Cytometry Online Lecture Series | B2672: 0 | C2672: Each | D2672: 2350 | E2672: List Price | F2672: US Dollar | G2672: N9-90107 | H2672: 68302
A2673: Cytek Spectral Cytometry On-site Instrument Training | B2673: 0 | C2673: Each | D2673: 7164 | E2673: List Price | F2673: US Dollar | G2673: N9-90108 | H2673: 68303
A2674: Cytek Spectral Cytometry Remote Instrument Training | B2674: 0 | C2674: Each | D2674: 2271 | E2674: List Price | F2674: US Dollar | G2674: N9-90109 | H2674: 68304
A2675: Aurora-CS 3- Laser (B/R/V) - Value | B2675: 0 | C2675: Each | D2675: 24134 | E2675: List Price | F2675: US Dollar | G2675: N9-90110 | H2675: 109580
A2676: Aurora-CS 3- Laser (B/R/V) - Value | B2676: 0 | C2676: Each | D2676: 20688 | E2676: List Price | F2676: US Dollar | G2676: N9-90110-INA | H2676: 105451
A2677: Aurora-CS 4- Laser (B/R/V/YG) - Value | B2677: 0 | C2677: Each | D2677: 29090 | E2677: List Price | F2677: US Dollar | G2677: N9-90112 | H2677: 109581
... A2898: ImageStream Preventative Maintenance Service | B2898: 0 | C2898: Each | D2898: 9800 | E2898: List Price | F2898: US Dollar | G2898: PM-IMAGESTREAM | H2898: 166565
B2899: 0 | C2899: Each | D2899: 642.9 | E2899: List Price | F2899: US Dollar | G2899: Pre-amp Board Test Station | H2899: 43870
A2900: cFluor®R720 anti-Mouse/Human CD44 (IM7), 25 tests (Kit Only) | B2900: 0.34 | C2900: Each | D2900: 95 | E2900: List Price | F2900: US Dollar | G2900: R6-20030 | H2900: 258013
A2901: cFluor™ B520 Anti-Human CD3 (SK7) | B2901: 1 | C2901: Each | D2901: 416 | E2901: List Price | F2901: US Dollar | G2901: R7-11001 | H2901: 127838
A2902: Fluorochrome: cFluor™ B520
A2903: Clone: SK7
A2904: Isotype: IgG1, kappa
A2905: Host: Mouse
A2906: Size: 100 Tests
A2907: cFluor™ B520 Anti-Human CD3 (SK7) | B2907: 0.85 | C2907: Each | D2907: 167 | E2907: List Price | F2907: US Dollar | G2907: R7-11002 | H2907: 127839
A2908: Size: 25 Tests
A2909: cFluor BYG781 Anti-Human CD4 (SK3) | B2909: 0.91 | C2909: Each | D2909: 564 | E2909: List Price | F2909: US Dollar | G2909: R7-11003 | H2909: 127832
A2910: Fluorochrome: cFluor BYG781
A2911: Clone: SK3
A2912: cFluor BYG781 Anti-Human CD4 (SK3) | B2912: 0.85 | C2912: Each | D2912: 162 | E2912: List Price | F2912: US Dollar | G2912: R7-11004 | H2912: 127833
A2913: cFluor R780 Anti-Human CD8 (SK1) | B2913: 1 | C2913: Each | D2913: 513 | E2913: List Price | F2913: US Dollar | G2913: R7-11005 | H2913: 128126
A2914: Fluorochrome: cFluor R780
A2915: Clone: SK1
A2916: cFluor R780 Anti-Human CD8 (SK1) | B2916: 0.85 | C2916: Each | D2916: 146 | E2916: List Price | F2916: US Dollar | G2916: R7-11006 | H2916: 127837
A2917: cFluor™ BYG575 Anti-Human CD16 (3G8) | B2917: 1 | C2917: Each | D2917: 405 | E2917: List Price | F2917: US Dollar | G2917: R7-11007 | H2917: 128226
A2918: Fluorochrome: cFluor™ BYG575
A2919: Clone: 3G8
A2920: cFluor™ BYG575 Anti-Human CD16 (3G8) | B2920: 0.85 | C2920: Each | D2920: 108 | E2920: List Price | F2920: US Dollar | G2920: R7-11008 | H2920: 128227
A2921: cFluor™ B690 Anti-Human CD45 (2D1) | B2921: 1 | C2921: Each | D2921: 443 | E2921: List Price | F2921: US Dollar | G2921: R7-11009 | H2921: 127728
A2922: Fluorochrome: cFluor™ B690
A2923: Clone: 2D1
A2924: cFluor™ B690 Anti-Human CD45 (2D1) | B2924: 0.85 | C2924: Each | D2924: 119 | E2924: List Price | F2924: US Dollar | G2924: R7-11010 | H2924: 127843
A2925: cFluor™ V547 Anti-Human CD45 (HI30) | B2925: 2.42 | C2925: Each | D2925: 564 | E2925: List Price | F2925: US Dollar | G2925: R7-11011 | H2925: 127844
A2926: Fluorochrome: cFluor™ V547
A2927: Clone: HI30
A2928: Size 100 Tests
A2929: cFluor™ V547 Anti-Human CD45 (HI30) | B2929: 1.22 | C2929: Each | D2929: 226 | E2929: List Price | F2929: US Dollar | G2929: R7-11012 | H2929: 128325
A2930: Size 25 Tests
A2931: cFluor BYG610 Anti-Human CD8 (SK1) | B2931: 1 | C2931: Each | D2931: 513 | E2931: List Price | F2931: US Dollar | G2931: R7-11013 | H2931: 127929
A2932: Fluorochrome: cFluor BYG610
A2933: cFluor BYG610 Anti-Human CD8 (SK1) | B2933: 0.85 | C2933: Each | D2933: 146 | E2933: List Price | F2933: US Dollar | G2933: R7-11014 | H2933: 127727
A2934: cFluor™ BYG575 Anti-Human CD56 (5.1H11) | B2934: 1 | C2934: Each | D2934: 445 | E2934: List Price | F2934: US Dollar | G2934: R7-11015 | H2934: 127930
A2935: Clone: 5.1H11
A2936: cFluor™ BYG575 Anti-Human CD56 (5.1H11) | B2936: 0.85 | C2936: Each | D2936: 179 | E2936: List Price | F2936: US Dollar | G2936: R7-11016 | H2936: 128326
A2937: cFluor® BYG610 Anti-Human CD33 (WM53) Format: cFluor® BYG610 Clone: WM53 Isotype: Mouse IgG1, kappa Size: 100Tests | B2937: 220.24 | C2937: Each | D2937: 368 | E2937: List Price | F2937: US Dollar | G2937: R7-11021 | H2937: 127845
A2938: cFluor® BYG610 Anti-Human CD33 (WM53) Format: cFluor® BYG610 Clone: WM53 Isotype: Mouse IgG1, kappa Size: 25 Tests | B2938: 56.7 | C2938: Each | D2938: 148 | E2938: List Price | F2938: US Dollar | G2938: R7-11022 | H2938: 128130
A2939: cFluor® BYG610 Anti-Human CD117 (104D2) | B2939: 42.73 | C2939: Each | D2939: 368 | E2939: List Price | F2939: US Dollar | G2939: R7-11023 | H2939: 128131
A2940: Fluorochrome: cFluor® BYG610
A2941: Clone: 104D2
A2942: Isotype: Mouse IgG1, kappa
A2943: cFluor® BYG610 Anti-Human CD117 (104D2) | B2943: 11.48 | C2943: Each | D2943: 148 | E2943: List Price | F2943: US Dollar | G2943: R7-11024 | H2943: 127846
A2944: cFluor™ B548 Anti-Human CD15 (HI98) | B2944: 11.81 | C2944: Each | D2944: 488 | E2944: List Price | F2944: US Dollar | G2944: R7-11025 | H2944: 128334
A2945: Fluorochrome: cFluor™ B548
A2946: Clone: HI98
A2947: Isotype: IgM, κ
A2948: cFluor™ B548 Anti-Human CD15 (HI98) | B2948: 3.6 | C2948: Each | D2948: 191 | E2948: List Price | F2948: US Dollar | G2948: R7-11026 | H2948: 128335
A2949: cFluor B515 Anti-Human CD4 (SK3) | B2949: 1.1 | C2949: Each | D2949: 416 | E2949: List Price | F2949: US Dollar | G2949: R7-11027 | H2949: 127725
A2950: Fluorochrome: cFluor B515
A2951: Isotype: IgG1, κ
...

Sheet Cytek Service Quoting Old
C2: ='FSE Input Old'!A3 -> Brad Ballard | F2: ="QUOTE#: "&'FSE Input Old'!$D$3&" "&'FSE Input Old'!$B$3 -> QUOTE#: MSU U0286
C3: ='FSE Input Old'!C3 -> Michigan State University
C4: ='FSE Input Old'!E3 -> 775 Woodlot Dr Bioengineering/IQ Building Rm 2315, East Lansing, Michigan 48824, U.S.
C7: Item | D7: Description | E7: Product Number | F7: Qty | G7: List Price | H7: Net Price | I7: Ext. Price
C8: =IF(D8="", "", "1") -> 1 | D8: =IF('FSE Input Old'!A7<>"", 'FSE Input Old'!A7, IF('FSE Input Old'!E7<>"", 'FSE Input Old'!E7, "")) -> On-Site Support (2 days) | E8: =IF('FSE Input Old'!B7<>"", 'FSE Input Old'!B7, IF('FSE Input Old'!F7<>"", 'FSE Input Old'!F7, "")) -> 60020 | F8: =IF(ISBLANK('FSE Input Old'!D7),"",'FSE Input Old'!D7) -> 1 | G8: =IF('FSE Input Old'!C7<>"", 'FSE Input Old'!C7, IF('FSE Input Old'!G7<>"", 'FSE Input Old'!G7, "")) -> 7571 | H8: =IF(G8="", "", IF(ISNUMBER(SEARCH("on-site", D8)), G8, IF(ISNUMBER(SEARCH("basic", 'FSE Input Old'!F$3)), G8*0.9, IF(ISNUMBER(SEARCH("value", 'FSE Input Old'!F$3)), G8-750, "") ) ) ) -> 7571 | I8: =IF(G8="","",H8*F8) -> 7571
C9: =IF(D9="", "", "2") -> 2 | D9: =IF('FSE Input Old'!A8<>"", 'FSE Input Old'!A8, IF('FSE Input Old'!E8<>"", 'FSE Input Old'!E8, "")) -> guava eacyCyte HT Preventative Maintenance | E9: =IF('FSE Input Old'!B8<>"", 'FSE Input Old'!B8, IF('FSE Input Old'!F8<>"", 'FSE Input Old'!F8, "")) -> PM-EASYCYTE-HT | F9: =IF(ISBLANK('FSE Input Old'!D8),"",'FSE Input Old'!D8) -> 1 | G9: =IF('FSE Input Old'!C8<>"", 'FSE Input Old'!C8, IF('FSE Input Old'!G8<>"", 'FSE Input Old'!G8, "")) -> 4814 | H9: =IF(G9="", "", IF(ISNUMBER(SEARCH("on-site", D9)), G9, IF(ISNUMBER(SEARCH("basic", 'FSE Input Old'!F$3)), G9*0.9, IF(ISNUMBER(SEARCH("value", 'FSE Input Old'!F$3)), G9-750, "") ) ) ) -> 4064 | I9: =IF(G9="","",H9*F9) -> 4064
C10: =IF(D10="", "", "3") -> 3 | D10: =IF('FSE Input Old'!A9<>"", 'FSE Input Old'!A9, IF('FSE Input Old'!E9<>"", 'FSE Input Old'!E9, "")) -> Sheath Filter, Rainbow | E10: =IF('FSE Input Old'!B9<>"", 'FSE Input Old'!B9, IF('FSE Input Old'!F9<>"", 'FSE Input Old'!F9, "")) -> N4-00025 | F10: =IF(ISBLANK('FSE Input Old'!D9),"",'FSE Input Old'!D9) -> 1 | G10: =IF('FSE Input Old'!C9<>"", 'FSE Input Old'!C9, IF('FSE Input Old'!G9<>"", 'FSE Input Old'!G9, "")) -> 192.45 | H10: =IF(G10="", "", IF(ISNUMBER(SEARCH("on-site", D10)), G10, IF(ISNUMBER(SEARCH("basic", 'FSE Input Old'!F$3)), G10*0.9, IF(ISNUMBER(SEARCH("value", 'FSE Input Old'!F$3)), G10-750, "") ) ) ) -> -557.55 | I10: =IF(G10="","",H10*F10) -> -557.55
C11: =IF(D11="", "", "4") | D11: =IF('FSE Input Old'!A10<>"", 'FSE Input Old'!A10, IF('FSE Input Old'!E10<>"", 'FSE Input Old'!E10, "")) | E11: =IF('FSE Input Old'!B10<>"", 'FSE Input Old'!B10, IF('FSE Input Old'!F10<>"", 'FSE Input Old'!F10, "")) | F11: =IF(ISBLANK('FSE Input Old'!D10),"",'FSE Input Old'!D10) | G11: =IF('FSE Input Old'!C10<>"", 'FSE Input Old'!C10, IF('FSE Input Old'!G10<>"", 'FSE Input Old'!G10, "")) | H11: =IF(G11="", "", IF(ISNUMBER(SEARCH("on-site", D11)), G11, IF(ISNUMBER(SEARCH("basic", 'FSE Input Old'!F$3)), G11*0.9, IF(ISNUMBER(SEARCH("value", 'FSE Input Old'!F$3)), G11-750, "") ) ) ) | I11: =IF(G11="","",H11*F11)
C13: Shipping & Handling Estimate
C14: Total | I14: =SUM(I15,I8:I11) -> 11077.45
G49: ="QUOTE#: "&'FSE Input Old'!$D$3&" "&'FSE Input Old'!$B$3 -> QUOTE#: MSU U0286
G101: ="QUOTE#: "&'FSE Input Old'!$D$3&" "&'FSE Input Old'!$B$3 -> QUOTE#: MSU U0286
G153: ="QUOTE#: "&'FSE Input Old'!$D$3&" "&'FSE Input Old'!$B$3 -> QUOTE#: MSU U0286

Sheet FSE Input Old
A1: CUSTOMER INFORMATION
A2: Name of customer requesting service/part: | B2: Instrument SN: | C2: Facility name: | D2: Shortened Facility name (ex. BCH): | E2: Facility Address: | F2: Contract type:
A3: Brad Ballard | B3: U0286 | C3: =VLOOKUP(B3,'Asset Data'!C2:U3586,2,FALSE) -> Michigan State University | D3: =VLOOKUP(C3,'Asset Data'!D1:E3586,2,FALSE) -> MSU | E3: =VLOOKUP(B3,'Asset Data'!C2:U3586,19,FALSE) -> 775 Woodlot Dr Bioengineering/IQ Building Rm 2315, East Lansing, Michigan 48824, U.S. | F3: =VLOOKUP(B3,'Asset Data'!C2:U3586,9,FALSE) -> Value
A5: SERVICE TYPE / PART NAME
A6: Service Type/ Part Name | B6: Service Type/Part Number | C6: Service Type/ Part Price | D6: Quantity | E6: Service Type / Part Name (if not listed) | F6: Service Type Part Number (if not listed) | G6: Price of Service Type / Part (if not listed)
A7: On-Site Support (2 days) | B7: =IF(A7="","",VLOOKUP(A7,'Pricing Data'!A$2:H5436,7,FALSE)) -> 60020 | C7: =IF(A7="","",VLOOKUP(A7,'Pricing Data'!A2:H5436,4,FALSE)) -> 7571 | D7: 1
A8: guava eacyCyte HT Preventative Maintenance | B8: =IF(A8="","",VLOOKUP(A8,'Pricing Data'!A$2:H5437,7,FALSE)) -> PM-EASYCYTE-HT | C8: =IF(A8="","",VLOOKUP(A8,'Pricing Data'!A2:H5437,4,FALSE)) -> 4814 | D8: 1
A9: Sheath Filter, Rainbow | B9: =IF(A9="","",VLOOKUP(A9,'Pricing Data'!A$2:H5438,7,FALSE)) -> N4-00025 | C9: =IF(A9="","",VLOOKUP(A9,'Pricing Data'!A2:H5438,4,FALSE)) -> 192.45 | D9: 1
B10: =IF(A10="","",VLOOKUP(A10,'Pricing Data'!A2:H5439,7,FALSE)) | C10: =IF(A10="","",VLOOKUP(A10,'Pricing Data'!A2:H5439,4,FALSE))
B18: Name of customer requesting service/part: | C18: Brad Ballard | E18: SERVICE TYPE / PART NAME | F18: Service Type/ Part Name | G18: On-Site Support (2 days) | H18: guava eacyCyte HT Preventative Maintenance | I18: Sheath Filter, Rainbow
B19: Instrument SN: | C19: U0286 | F19: Service Type/Part Number | G19: =IF(G18="","",VLOOKUP(G18,'Pricing Data'!$B18:HAB25,7,FALSE)) -> #N/A | H19: =IF(H18="","",VLOOKUP(H18,'Pricing Data'!$B18:HAC25,7,FALSE)) -> #N/A | I19: =IF(I18="","",VLOOKUP(I18,'Pricing Data'!$B18:HAD25,7,FALSE)) -> #N/A | J19: =IF(J18="","",VLOOKUP(J18,'Pricing Data'!B18:HAE25,7,FALSE))
B20: Facility name: | C20: =VLOOKUP(C19,'Asset Data'!B20:EGX38,2,FALSE) -> #N/A | F20: Service Type/ Part Price | G20: =IF(G18="","",VLOOKUP(G18,'Pricing Data'!B18:HAB25,4,FALSE)) -> #N/A | H20: =IF(H18="","",VLOOKUP(H18,'Pricing Data'!B18:HAC25,4,FALSE)) -> #N/A | I20: =IF(I18="","",VLOOKUP(I18,'Pricing Data'!B18:HAD25,4,FALSE)) -> #N/A | J20: =IF(J18="","",VLOOKUP(J18,'Pricing Data'!B18:HAE25,4,FALSE))
B21: Shortened Facility name (ex. BCH): | C21: =VLOOKUP(C20,'Asset Data'!A21:EGX22,2,FALSE) -> #N/A | F21: Quantity | G21: 1 | H21: 1 | I21: 1
B22: Facility Address: | C22: =VLOOKUP(C19,'Asset Data'!B20:EGX38,19,FALSE) -> #N/A | F22: Service Type / Part Name (if not listed)
B23: Contract type: | C23: =VLOOKUP(C19,'Asset Data'!B20:EGX38,9,FALSE) -> #N/A | F23: Service Type Part Number (if not listed)
F24: Price of Service Type / Part (if not listed)
A32: SERVICE TYPE/PART NAME - SERVICE QUOTE
B33: Part 1 | C33: Part 2 | D33: Part 3 | E33: Part 4
A34: Service Type/ Part Name | B34: On-Site Support (2 days) | C34: guava eacyCyte HT Preventative Maintenance | D34: Sheath Filter, Rainbow
A35: Service Type/Part Number | B35: =IF(B34="","",VLOOKUP(B34,'Pricing Data'!$B31:GZX38,7,FALSE)) -> #N/A | C35: =IF(C34="","",VLOOKUP(C34,'Pricing Data'!$B31:GZY38,7,FALSE)) -> #N/A | D35: =IF(D34="","",VLOOKUP(D34,'Pricing Data'!$B31:GZZ38,7,FALSE)) -> #N/A | E35: =IF(E34="","",VLOOKUP(E34,'Pricing Data'!#REF!,7,FALSE))
A36: Service Type/ Part Price | B36: =IF(B34="","",VLOOKUP(B34,'Pricing Data'!#REF!,4,FALSE)) -> #REF! | C36: =IF(C34="","",VLOOKUP(C34,'Pricing Data'!#REF!,4,FALSE)) -> #REF! | D36: =IF(D34="","",VLOOKUP(D34,'Pricing Data'!#REF!,4,FALSE)) -> #REF! | E36: =IF(E34="","",VLOOKUP(E34,'Pricing Data'!#REF!,4,FALSE))
A37: Quantity | B37: 1 | C37: 1 | D37: 1
A38: Service Type / Part Name (if not listed)
A39: Service Type Part Number (if not listed)
A40: Price of Service Type / Part (if not listed)
